Workbook

Sheet EERR Mensual
A1: CASA ORTIZ | J1: AÑO 1 | X1: AÑO 2 | AL1: AÑO 2
I2: 0 | J2: 1 | K2: 2 | L2: 3 | M2: 4 | N2: 5 | O2: 6 | P2: 7 | Q2: 8 | R2: 9 | S2: 10 | T2: 11 | U2: 12 | X2: 1 | Y2: 2 | Z2: 3 | AA2: 4 | AB2: 5 | AC2: 6 | AD2: 7 | AE2: 8 | AF2: 9 | AG2: 10 | AH2: 11 | AI2: 12 | AL2: 1 | AM2: 2 | AN2: 3 | AO2: 4 | AP2: 5 | AQ2: 6 | AR2: 7 | AS2: 8 | AT2: 9 | AU2: 10 | AV2: 11 | AW2: 12
J3: Ago | K3: Sep | L3: Oct | M3: Nov | N3: Dic | O3: Ene | P3: Feb | Q3: Mar | R3: Abr | S3: May | T3: Jun | U3: Jul | X3: Ago | Y3: Sep | Z3: Oct | AA3: Nov | AB3: Dic | AC3: Ene | AD3: Feb | AE3: Mar | AF3: Abr | AG3: May | AH3: Jun | AI3: Jul | AL3: Ago | AM3: Sep | AN3: Oct | AO3: Nov | AP3: Dic | AQ3: Ene | AR3: Feb | AS3: Mar | AT3: Abr | AU3: May | AV3: Jun | AW3: Jul
B4: Precision Cubiertos | C4: 1 | F4: Estado de Resultados
F5: Ventas | J5: =J6*$C$6 -> 1.4106362e+08 | K5: =K6*$C$6 -> 163970730 | L5: =L6*$C$6 -> 158149530 | M5: =M6*$C$6 -> 2.3407634e+08 | N5: =N6*$C$6 -> 186981795 | O5: =O6*$C$6 -> 1.3191428e+08 | P5: =P6*$C$6 -> 156056670 | Q5: =Q6*$C$6 -> 2.2076381e+08 | ... U5: =U6*$C$6 -> 2.641716e+08 | X5: =X6*$C$6 -> 1.5388758e+08 | Y5: =Y6*$C$6 -> 273284550 | Z5: =Z6*$C$6 -> 2.6358255e+08 | AA5: =AA6*$C$6 -> 3.6011745e+08 | AB5: =AB6*$C$6 -> 287664300 | AC5: =AC6*$C$6 -> 2.0294505e+08 | AD5: =AD6*$C$6 -> 2.229381e+08 | AE5: =AE6*$C$6 -> 294351750 | ... AI5: =AI6*$C$6 -> 2.641716e+08 | AL5: =AL6*$C$6 -> 233163000 | AM5: =AM6*$C$6 -> 248440500 | AN5: =AN6*$C$6 -> 239620500 | AO5: =AO6*$C$6 -> 327379500 | AP5: =AP6*$C$6 -> 261513000 | AQ5: =AQ6*$C$6 -> 184495500 | AR5: =AR6*$C$6 -> 202671000 | AS5: =AS6*$C$6 -> 267592500 | ... AW5: =AW6*$C$6 -> 240156000
B6: Ticket Promedio | C6: 31500 | G6: Cubiertos | J6: =(J8*J7)*$C$4 -> 4478.21 | K6: =(K8*K7)*$C$4 -> 5205.42 | L6: =(L8*L7)*$C$4 -> 5020.62 | M6: =(M8*M7)*$C$4 -> 7430.995 | N6: =(N8*N7)*$C$4 -> 5935.93 | O6: =(O8*O7)*$C$4 -> 4187.755 | P6: =(P8*P7)*$C$4 -> 4954.18 | Q6: =(Q8*Q7)*$C$4 -> 7008.375 | ... U6: =(U8*U7)*$C$4 -> 8386.4 | X6: =(X8*X7)*$C$4 -> 4885.32 | Y6: =(Y8*Y7)*$C$4 -> 8675.7 | Z6: =(Z8*Z7)*$C$4 -> 8367.7 | AA6: =(AA8*AA7)*$C$4 -> 11432.3 | AB6: =(AB8*AB7)*$C$4 -> 9132.2 | AC6: =(AC8*AC7)*$C$4 -> 6442.7 | AD6: =(AD8*AD7)*$C$4 -> 7077.4 | AE6: =(AE8*AE7)*$C$4 -> 9344.5 | ... AI6: =(AI8*AI7)*$C$4 -> 8386.4 | AL6: =(AL8*AL7)*$C$4 -> 7402 | AM6: =(AM8*AM7)*$C$4 -> 7887 | AN6: =(AN8*AN7)*$C$4 -> 7607 | AO6: =(AO8*AO7)*$C$4 -> 10393 | AP6: =(AP8*AP7)*$C$4 -> 8302 | AQ6: =(AQ8*AQ7)*$C$4 -> 5857 | AR6: =(AR8*AR7)*$C$4 -> 6434 | AS6: =(AS8*AS7)*$C$4 -> 8495 | ... AW6: =(AW8*AW7)*$C$4 -> 7624
G7: Ramp - up | J7: 0.55 | K7: 0.6 | L7: 0.6 | M7: 0.65 | N7: 0.65 | O7: 0.65 | P7: 0.7 | Q7: 0.75 | R7: 0.8 | S7: 0.85 | T7: 0.9 | U7: 1 | X7: 0.6 | Y7: 1 | Z7: 1 | AA7: 1 | AB7: 1 | AC7: 1 | AD7: 1 | AE7: 1 | AF7: 1 | AG7: 1 | AH7: 1 | AI7: 1 | AL7: 1 | AM7: 1 | AN7: 1 | AO7: 1 | AP7: 1 | AQ7: 1 | AR7: 1 | AS7: 1 | AT7: 1 | AU7: 1 | AV7: 1 | AW7: 1
B8: Porcentaje CMV | C8: 0.34 | G8: Proyeccion Ventas | J8: 8142.2 | K8: 8675.7 | L8: 8367.7 | M8: 11432.3 | N8: 9132.2 | O8: 6442.7 | P8: 7077.4 | Q8: 9344.5 | R8: 9356.6 | S8: 8954 | T8: 6920.1 | U8: 8386.4 | X8: 8142.2 | Y8: 8675.7 | Z8: 8367.7 | AA8: 11432.3 | AB8: 9132.2 | AC8: 6442.7 | AD8: 7077.4 | AE8: 9344.5 | AF8: 9356.6 | AG8: 8954 | AH8: 6920.1 | AI8: 8386.4 | AL8: 7402 | AM8: 7887 | AN8: 7607 | AO8: 10393 | AP8: 8302 | AQ8: 5857 | AR8: 6434 | AS8: 8495 | AT8: 8506 | AU8: 8140 | AV8: 6291 | AW8: 7624
X9: =+X8*1.03 -> 8386.466 | Y9: =+Y8*1.05 -> 9109.485 | Z9: =+Z8*1.05 -> 8786.085 | AA9: =+AA8*1.05 -> 12003.915 | AB9: =+AB8*1.05 -> 9588.81 | AC9: =+AC8*1.05 -> 6764.835 | AD9: =+AD8*1.05 -> 7431.27 | AE9: =+AE8*1.05 -> 9811.725 | AF9: =+AF8*1.05 -> 9824.43 | ... AI9: =+AI8*1.05 -> 8805.72
B10: Costo Delivery | C10: 0.015 | F10: Costos Variables | J10: =SUM(J11:J18) -> 69121171 | K10: =SUM(K11:K18) -> 80345658 | L10: =SUM(L11:L18) -> 77493270 | M10: =SUM(M11:M18) -> 1.1469741e+08 | N10: =SUM(N11:N18) -> 91621080 | O10: =SUM(O11:O18) -> 64637998 | P10: =SUM(P11:P18) -> 76467768 | Q10: =SUM(Q11:Q18) -> 1.0817427e+08 | ... U10: =SUM(U11:U18) -> 1.2944408e+08 | X10: =SUM(X11:X18) -> 75404914 | Y10: =SUM(Y11:Y18) -> 1.3390943e+08 | Z10: =SUM(Z11:Z18) -> 1.2915545e+08 | AA10: =SUM(AA11:AA18) -> 1.7645755e+08 | AB10: =SUM(AB11:AB18) -> 140955507 | AC10: =SUM(AC11:AC18) -> 99443075 | AD10: =SUM(AD11:AD18) -> 1.0923967e+08 | AE10: =SUM(AE11:AE18) -> 1.4423236e+08 | ... AI10: =SUM(AI11:AI18) -> 1.2944408e+08 | AL10: =SUM(AL11:AL18) -> 114249870 | AM10: =SUM(AM11:AM18) -> 121735845 | AN10: =SUM(AN11:AN18) -> 117414045 | AO10: =SUM(AO11:AO18) -> 160415955 | AP10: =SUM(AP11:AP18) -> 128141370 | AQ10: =SUM(AQ11:AQ18) -> 90402795 | AR10: =SUM(AR11:AR18) -> 99308790 | AS10: =SUM(AS11:AS18) -> 131120325 | ... AW10: =SUM(AW11:AW18) -> 117676440
F11: Proveedores | G11: Costo de mercadería | J11: =J5*$C$8 -> 47961629 | K11: =K5*$C$8 -> 55750048 | L11: =L5*$C$8 -> 53770840 | M11: =M5*$C$8 -> 79585956 | N11: =N5*$C$8 -> 63573810 | O11: =O5*$C$8 -> 44850856 | P11: =P5*$C$8 -> 53059268 | Q11: =Q5*$C$8 -> 75059696 | ... U11: =U5*$C$8 -> 89818344 | X11: =X5*$C$8 -> 52321777 | Y11: =Y5*$C$8 -> 92916747 | Z11: =Z5*$C$8 -> 89618067 | AA11: =AA5*$C$8 -> 1.2243993e+08 | AB11: =AB5*$C$8 -> 97805862 | AC11: =AC5*$C$8 -> 69001317 | AD11: =AD5*$C$8 -> 75798954 | AE11: =AE5*$C$8 -> 100079595 | ... AI11: =AI5*$C$8 -> 89818344 | AL11: =AL5*$C$8 -> 79275420 | AM11: =AM5*$C$8 -> 84469770 | AN11: =AN5*$C$8 -> 81470970 | AO11: =AO5*$C$8 -> 1.1130903e+08 | AP11: =AP5*$C$8 -> 88914420 | AQ11: =AQ5*$C$8 -> 62728470 | AR11: =AR5*$C$8 -> 68908140 | AS11: =AS5*$C$8 -> 90981450 | ... AW11: =AW5*$C$8 -> 81653040
B12: Gastos Adición | C12: 0.0025 | F12: Proveedores | G12: Costo delivery | J12: =J5*$C$10 -> 2115954.2 | K12: =K5*$C$10 -> 2459560.9 | L12: =L5*$C$10 -> 2372242.9 | M12: =M5*$C$10 -> 3511145.1 | N12: =N5*$C$10 -> 2804726.9 | O12: =O5*$C$10 -> 1978714.2 | P12: =P5*$C$10 -> 2340850 | Q12: =Q5*$C$10 -> 3311457.2 | ... U12: =U5*$C$10 -> 3962574 | X12: =X5*$C$10 -> 2308313.7 | Y12: =Y5*$C$10 -> 4099268.2 | Z12: =Z5*$C$10 -> 3953738.3 | AA12: =AA5*$C$10 -> 5401761.8 | AB12: =AB5*$C$10 -> 4314964.5 | AC12: =AC5*$C$10 -> 3044175.8 | AD12: =AD5*$C$10 -> 3344071.5 | AE12: =AE5*$C$10 -> 4415276.2 | ... AI12: =AI5*$C$10 -> 3962574 | AL12: =AL5*$C$10 -> 3497445 | AM12: =AM5*$C$10 -> 3726607.5 | AN12: =AN5*$C$10 -> 3594307.5 | AO12: =AO5*$C$10 -> 4910692.5 | AP12: =AP5*$C$10 -> 3922695 | AQ12: =AQ5*$C$10 -> 2767432.5 | AR12: =AR5*$C$10 -> 3040065 | AS12: =AS5*$C$10 -> 4013887.5 | ... AW12: =AW5*$C$10 -> 3602340
F13: Proveedores | G13: Gastos adición | J13: =J5*$C$12 -> 352659.04 | K13: =K5*$C$12 -> 409926.83 | L13: =L5*$C$12 -> 395373.83 | M13: =M5*$C$12 -> 585190.86 | N13: =N5*$C$12 -> 467454.49 | O13: =O5*$C$12 -> 329785.71 | P13: =P5*$C$12 -> 390141.67 | Q13: =Q5*$C$12 -> 551909.53 | ... U13: =U5*$C$12 -> 660429 | X13: =X5*$C$12 -> 384718.95 | Y13: =Y5*$C$12 -> 683211.38 | Z13: =Z5*$C$12 -> 658956.38 | AA13: =AA5*$C$12 -> 900293.63 | AB13: =AB5*$C$12 -> 719160.75 | AC13: =AC5*$C$12 -> 507362.63 | AD13: =AD5*$C$12 -> 557345.25 | AE13: =AE5*$C$12 -> 735879.38 | ... AI13: =AI5*$C$12 -> 660429 | AL13: =AL5*$C$12 -> 582907.5 | AM13: =AM5*$C$12 -> 621101.25 | AN13: =AN5*$C$12 -> 599051.25 | AO13: =AO5*$C$12 -> 818448.75 | AP13: =AP5*$C$12 -> 653782.5 | AQ13: =AQ5*$C$12 -> 461238.75 | AR13: =AR5*$C$12 -> 506677.5 | AS13: =AS5*$C$12 -> 668981.25 | ... AW13: =AW5*$C$12 -> 600390
B14: Com. / Impuestos | C14: 0.11 | G14: Com. / Impuestos (Incluye Iva) | J14: =J5*$C$14 -> 15516998 | K14: =K5*$C$14 -> 18036780 | L14: =L5*$C$14 -> 17396448 | M14: =M5*$C$14 -> 25748398 | N14: =N5*$C$14 -> 20567997 | O14: =O5*$C$14 -> 14510571 | P14: =P5*$C$14 -> 17166234 | Q14: =Q5*$C$14 -> 24284019 | ... U14: =U5*$C$14 -> 29058876 | X14: =X5*$C$14 -> 16927634 | Y14: =Y5*$C$14 -> 30061300 | Z14: =Z5*$C$14 -> 28994081 | AA14: =AA5*$C$14 -> 39612920 | AB14: =AB5*$C$14 -> 31643073 | AC14: =AC5*$C$14 -> 22323956 | AD14: =AD5*$C$14 -> 24523191 | AE14: =AE5*$C$14 -> 32378692 | ... AI14: =AI5*$C$14 -> 29058876 | AL14: =AL5*$C$14 -> 25647930 | AM14: =AM5*$C$14 -> 27328455 | AN14: =AN5*$C$14 -> 26358255 | AO14: =AO5*$C$14 -> 36011745 | AP14: =AP5*$C$14 -> 28766430 | AQ14: =AQ5*$C$14 -> 20294505 | AR14: =AR5*$C$14 -> 22293810 | AS14: =AS5*$C$14 -> 29435175 | ... AW14: =AW5*$C$14 -> 26417160
F15: Proveedores | G15: Mantenimiento | J15: =J5*$C$20 -> 1410636.2 | K15: =K5*$C$20 -> 1639707.3 | L15: =L5*$C$20 -> 1581495.3 | M15: =M5*$C$20 -> 2340763.4 | N15: =N5*$C$20 -> 1869817.9 | O15: =O5*$C$20 -> 1319142.8 | P15: =P5*$C$20 -> 1560566.7 | Q15: =Q5*$C$20 -> 2207638.1 | ... U15: =U5*$C$20 -> 2641716 | X15: =X5*$C$20 -> 1538875.8 | Y15: =Y5*$C$20 -> 2732845.5 | Z15: =Z5*$C$20 -> 2635825.5 | AA15: =AA5*$C$20 -> 3601174.5 | AB15: =AB5*$C$20 -> 2876643 | AC15: =AC5*$C$20 -> 2029450.5 | AD15: =AD5*$C$20 -> 2229381 | AE15: =AE5*$C$20 -> 2943517.5 | ... AI15: =AI5*$C$20 -> 2641716 | AL15: =AL5*$C$20 -> 2331630 | AM15: =AM5*$C$20 -> 2484405 | AN15: =AN5*$C$20 -> 2396205 | AO15: =AO5*$C$20 -> 3273795 | AP15: =AP5*$C$20 -> 2615130 | AQ15: =AQ5*$C$20 -> 1844955 | AR15: =AR5*$C$20 -> 2026710 | AS15: =AS5*$C$20 -> 2675925 | ... AW15: =AW5*$C$20 -> 2401560
B16: Marketing | C16: 2000000 | F16: Proveedores | G16: Bazar | J16: =J5*$C$26 -> 352659.04 | K16: =K5*$C$26 -> 409926.83 | L16: =L5*$C$26 -> 395373.83 | M16: =M5*$C$26 -> 585190.86 | N16: =N5*$C$26 -> 467454.49 | O16: =O5*$C$26 -> 329785.71 | P16: =P5*$C$26 -> 390141.67 | Q16: =Q5*$C$26 -> 551909.53 | ... U16: =U5*$C$26 -> 660429 | X16: =X5*$C$26 -> 384718.95 | Y16: =Y5*$C$26 -> 683211.38 | Z16: =Z5*$C$26 -> 658956.38 | AA16: =AA5*$C$26 -> 900293.63 | AB16: =AB5*$C$26 -> 719160.75 | AC16: =AC5*$C$26 -> 507362.63 | AD16: =AD5*$C$26 -> 557345.25 | AE16: =AE5*$C$26 -> 735879.38 | ... AI16: =AI5*$C$26 -> 660429 | AL16: =AL5*$C$26 -> 582907.5 | AM16: =AM5*$C$26 -> 621101.25 | AN16: =AN5*$C$26 -> 599051.25 | AO16: =AO5*$C$26 -> 818448.75 | AP16: =AP5*$C$26 -> 653782.5 | AQ16: =AQ5*$C$26 -> 461238.75 | AR16: =AR5*$C$26 -> 506677.5 | AS16: =AS5*$C$26 -> 668981.25 | ... AW16: =AW5*$C$26 -> 600390
F17: Proveedores | G17: Inversión | J17: =J5*$C$28 -> 1410636.2 | K17: =K5*$C$28 -> 1639707.3 | L17: =L5*$C$28 -> 1581495.3 | M17: =M5*$C$28 -> 2340763.4 | N17: =N5*$C$28 -> 1869817.9 | O17: =O5*$C$28 -> 1319142.8 | P17: =P5*$C$28 -> 1560566.7 | Q17: =Q5*$C$28 -> 2207638.1 | ... U17: =U5*$C$28 -> 2641716 | X17: =X5*$C$28 -> 1538875.8 | Y17: =Y5*$C$28 -> 2732845.5 | Z17: =Z5*$C$28 -> 2635825.5 | AA17: =AA5*$C$28 -> 3601174.5 | AB17: =AB5*$C$28 -> 2876643 | AC17: =AC5*$C$28 -> 2029450.5 | AD17: =AD5*$C$28 -> 2229381 | AE17: =AE5*$C$28 -> 2943517.5 | ... AI17: =AI5*$C$28 -> 2641716 | AL17: =AL5*$C$28 -> 2331630 | AM17: =AM5*$C$28 -> 2484405 | AN17: =AN5*$C$28 -> 2396205 | AO17: =AO5*$C$28 -> 3273795 | AP17: =AP5*$C$28 -> 2615130 | AQ17: =AQ5*$C$28 -> 1844955 | AR17: =AR5*$C$28 -> 2026710 | AS17: =AS5*$C$28 -> 2675925 | ... AW17: =AW5*$C$28 -> 2401560
B18: Nomina Full | C18: 60000000
F19: Márgen Bruto | H19: ARS | J19: =J5-J10 -> 71942444 | K19: =K5-K10 -> 83625072 | L19: =L5-L10 -> 80656260 | M19: =M5-M10 -> 1.1937893e+08 | N19: =N5-N10 -> 95360715 | O19: =O5-O10 -> 67276284 | P19: =P5-P10 -> 79588902 | Q19: =Q5-Q10 -> 1.1258954e+08 | ... U19: =U5-U10 -> 1.3472752e+08 | W19: ARS | X19: =X5-X10 -> 78482666 | Y19: =Y5-Y10 -> 1.3937512e+08 | Z19: =Z5-Z10 -> 1.344271e+08 | AA19: =AA5-AA10 -> 1.836599e+08 | AB19: =AB5-AB10 -> 146708793 | AC19: =AC5-AC10 -> 1.0350198e+08 | AD19: =AD5-AD10 -> 1.1369843e+08 | AE19: =AE5-AE10 -> 1.5011939e+08 | ... AI19: =AI5-AI10 -> 1.3472752e+08 | AK19: ARS | AL19: =AL5-AL10 -> 118913130 | AM19: =AM5-AM10 -> 126704655 | AN19: =AN5-AN10 -> 122206455 | AO19: =AO5-AO10 -> 166963545 | AP19: =AP5-AP10 -> 133371630 | AQ19: =AQ5-AQ10 -> 94092705 | AR19: =AR5-AR10 -> 103362210 | AS19: =AS5-AS10 -> 136472175 | ... AW19: =AW5-AW10 -> 122479560
B20: Mantenimiento | C20: 0.01 | H20: % | J20: =J19/J5 -> 0.51 | K20: =K19/K5 -> 0.51 | L20: =L19/L5 -> 0.51 | M20: =M19/M5 -> 0.51 | N20: =N19/N5 -> 0.51 | O20: =O19/O5 -> 0.51 | P20: =P19/P5 -> 0.51 | Q20: =Q19/Q5 -> 0.51 | ... U20: =U19/U5 -> 0.51 | W20: % | X20: =X19/X5 -> 0.51 | Y20: =Y19/Y5 -> 0.51 | Z20: =Z19/Z5 -> 0.51 | AA20: =AA19/AA5 -> 0.51 | AB20: =AB19/AB5 -> 0.51 | AC20: =AC19/AC5 -> 0.51 | AD20: =AD19/AD5 -> 0.51 | AE20: =AE19/AE5 -> 0.51 | ... AI20: =AI19/AI5 -> 0.51 | AK20: % | AL20: =AL19/AL5 -> 0.51 | AM20: =AM19/AM5 -> 0.51 | AN20: =AN19/AN5 -> 0.51 | AO20: =AO19/AO5 -> 0.51 | AP20: =AP19/AP5 -> 0.51 | AQ20: =AQ19/AQ5 -> 0.51 | AR20: =AR19/AR5 -> 0.51 | AS20: =AS19/AS5 -> 0.51 | ... AW20: =AW19/AW5 -> 0.51
B22: Gastos Operativos | C22: 3000000 | G22: Ramp - up Nómina | J22: 0.67 | K22: 0.67 | L22: 0.67 | M22: 0.75 | N22: 0.75 | O22: 0.67 | P22: 0.67 | Q22: 0.75 | R22: 0.75 | S22: 0.75 | T22: 0.75 | U22: 0.9 | X22: 1 | Y22: 1 | Z22: 1 | AA22: 1 | AB22: 1 | AC22: 1 | AD22: 1 | AE22: 1 | AF22: 1 | AG22: 1 | AH22: 1 | AI22: 1 | AL22: 1 | AM22: 1 | AN22: 1 | AO22: 1 | AP22: 1 | AQ22: 1 | AR22: 1 | AS22: 1 | AT22: 1 | AU22: 1 | AV22: 1 | AW22: 1
F23: Costos Estructura | J23: =SUM(J24:J33) -> 79036000 | K23: =SUM(K24:K33) -> 79036000 | L23: =SUM(L24:L33) -> 79036000 | M23: =SUM(M24:M33) -> 84236000 | N23: =SUM(N24:N33) -> 84236000 | O23: =SUM(O24:O33) -> 79036000 | P23: =SUM(P24:P33) -> 79036000 | Q23: =SUM(Q24:Q33) -> 84236000 | ... U23: =SUM(U24:U33) -> 93986000 | X23: =SUM(X24:X33) -> 100486000 | Y23: =SUM(Y24:Y33) -> 100486000 | Z23: =SUM(Z24:Z33) -> 100486000 | AA23: =SUM(AA24:AA33) -> 100486000 | AB23: =SUM(AB24:AB33) -> 100486000 | AC23: =SUM(AC24:AC33) -> 100486000 | AD23: =SUM(AD24:AD33) -> 100486000 | AE23: =SUM(AE24:AE33) -> 100486000 | ... AI23: =SUM(AI24:AI33) -> 100486000 | AL23: =SUM(AL24:AL33) -> 100486000 | AM23: =SUM(AM24:AM33) -> 100486000 | AN23: =SUM(AN24:AN33) -> 100486000 | AO23: =SUM(AO24:AO33) -> 100486000 | AP23: =SUM(AP24:AP33) -> 100486000 | AQ23: =SUM(AQ24:AQ33) -> 100486000 | AR23: =SUM(AR24:AR33) -> 100486000 | AS23: =SUM(AS24:AS33) -> 100486000 | ... AW23: =SUM(AW24:AW33) -> 100486000
B24: Honorarios | C24: 2300000 | F24: Proveedores | G24: RRHH | J24: =$C$18*J22 -> 40200000 | K24: =$C$18*K22 -> 40200000 | L24: =$C$18*L22 -> 40200000 | M24: =$C$18*M22 -> 45000000 | N24: =$C$18*N22 -> 45000000 | O24: =$C$18*O22 -> 40200000 | P24: =$C$18*P22 -> 40200000 | Q24: =$C$18*Q22 -> 45000000 | ... U24: =$C$18*U22 -> 54000000 | X24: =$C$18*X22 -> 60000000 | Y24: =$C$18*Y22 -> 60000000 | Z24: =$C$18*Z22 -> 60000000 | AA24: =$C$18*AA22 -> 60000000 | AB24: =$C$18*AB22 -> 60000000 | AC24: =$C$18*AC22 -> 60000000 | AD24: =$C$18*AD22 -> 60000000 | AE24: =$C$18*AE22 -> 60000000 | ... AI24: =$C$18*AI22 -> 60000000 | AL24: =$C$18*AL22 -> 60000000 | AM24: =$C$18*AM22 -> 60000000 | AN24: =$C$18*AN22 -> 60000000 | AO24: =$C$18*AO22 -> 60000000 | AP24: =$C$18*AP22 -> 60000000 | AQ24: =$C$18*AQ22 -> 60000000 | AR24: =$C$18*AR22 -> 60000000 | AS24: =$C$18*AS22 -> 60000000 | ... AW24: =$C$18*AW22 -> 60000000
F25: Proveedores | G25: Costo Locativo | J25: 12500000 | K25: 12500000 | L25: 12500000 | M25: 12500000 | N25: 12500000 | O25: 12500000 | P25: 12500000 | Q25: 12500000 | R25: 12500000 | S25: 12500000 | T25: 12500000 | U25: 12500000 | X25: 12500000 | Y25: 12500000 | Z25: 12500000 | AA25: 12500000 | AB25: 12500000 | AC25: 12500000 | AD25: 12500000 | AE25: 12500000 | AF25: 12500000 | AG25: 12500000 | AH25: 12500000 | AI25: 12500000 | AL25: 12500000 | AM25: 12500000 | AN25: 12500000 | AO25: 12500000 | AP25: 12500000 | AQ25: 12500000 | AR25: 12500000 | AS25: 12500000 | AT25: 12500000 | AU25: 12500000 | AV25: 12500000 | AW25: 12500000
B26: Bazar | C26: 0.0025 | F26: Proveedores | G26: Servicios públicos | J26: 6800000 | K26: 6800000 | L26: 6800000 | M26: 6800000 | N26: 6800000 | O26: 6800000 | P26: 6800000 | Q26: 6800000 | R26: 6800000 | S26: 6800000 | T26: 6800000 | U26: 6800000 | X26: 6800000 | Y26: 6800000 | Z26: 6800000 | AA26: 6800000 | AB26: 6800000 | AC26: 6800000 | AD26: 6800000 | AE26: 6800000 | AF26: 6800000 | AG26: 6800000 | AH26: 6800000 | AI26: 6800000 | AL26: 6800000 | AM26: 6800000 | AN26: 6800000 | AO26: 6800000 | AP26: 6800000 | AQ26: 6800000 | AR26: 6800000 | AS26: 6800000 | AT26: 6800000 | AU26: 6800000 | AV26: 6800000 | AW26: 6800000
F27: Proveedores | G27: Marketing | J27: =$C$16 -> 2000000 | K27: =$C$16 -> 2000000 | L27: =$C$16 -> 2000000 | M27: =$C$16 -> 2000000 | N27: =$C$16 -> 2000000 | O27: =$C$16 -> 2000000 | P27: =$C$16 -> 2000000 | Q27: =$C$16 -> 2000000 | ... U27: =$C$16 -> 2000000 | X27: =$C$16 -> 2000000 | Y27: =$C$16 -> 2000000 | Z27: =$C$16 -> 2000000 | AA27: =$C$16 -> 2000000 | AB27: =$C$16 -> 2000000 | AC27: =$C$16 -> 2000000 | AD27: =$C$16 -> 2000000 | AE27: =$C$16 -> 2000000 | ... AI27: =$C$16 -> 2000000 | AL27: =$C$16 -> 2000000 | AM27: =$C$16 -> 2000000 | AN27: =$C$16 -> 2000000 | AO27: =$C$16 -> 2000000 | AP27: =$C$16 -> 2000000 | AQ27: =$C$16 -> 2000000 | AR27: =$C$16 -> 2000000 | AS27: =$C$16 -> 2000000 | ... AW27: =$C$16 -> 2000000
B28: Inversión | C28: 0.01 | F28: Proveedores | G28: Gastos Operativos | J28: =$C$22 -> 3000000 | K28: =$C$22 -> 3000000 | L28: =$C$22 -> 3000000 | M28: =$C$22 -> 3000000 | N28: =$C$22 -> 3000000 | O28: =$C$22 -> 3000000 | P28: =$C$22 -> 3000000 | Q28: =$C$22 -> 3000000 | ... U28: =$C$22 -> 3000000 | X28: =$C$22 -> 3000000 | Y28: =$C$22 -> 3000000 | Z28: =$C$22 -> 3000000 | AA28: =$C$22 -> 3000000 | AB28: =$C$22 -> 3000000 | AC28: =$C$22 -> 3000000 | AD28: =$C$22 -> 3000000 | AE28: =$C$22 -> 3000000 | ... AI28: =$C$22 -> 3000000 | AL28: =$C$22 -> 3000000 | AM28: =$C$22 -> 3000000 | AN28: =$C$22 -> 3000000 | AO28: =$C$22 -> 3000000 | AP28: =$C$22 -> 3000000 | AQ28: =$C$22 -> 3000000 | AR28: =$C$22 -> 3000000 | AS28: =$C$22 -> 3000000 | ... AW28: =$C$22 -> 3000000
F29: Proveedores | G29: Honorarios | J29: =$C$24 -> 2300000 | K29: =$C$24 -> 2300000 | L29: =$C$24 -> 2300000 | M29: =$C$24 -> 2300000 | N29: =$C$24 -> 2300000 | O29: =$C$24 -> 2300000 | P29: =$C$24 -> 2300000 | Q29: =$C$24 -> 2300000 | ... U29: =$C$24 -> 2300000 | X29: =$C$24 -> 2300000 | Y29: =$C$24 -> 2300000 | Z29: =$C$24 -> 2300000 | AA29: =$C$24 -> 2300000 | AB29: =$C$24 -> 2300000 | AC29: =$C$24 -> 2300000 | AD29: =$C$24 -> 2300000 | AE29: =$C$24 -> 2300000 | ... AI29: =$C$24 -> 2300000 | AL29: =$C$24 -> 2300000 | AM29: =$C$24 -> 2300000 | AN29: =$C$24 -> 2300000 | AO29: =$C$24 -> 2300000 | AP29: =$C$24 -> 2300000 | AQ29: =$C$24 -> 2300000 | AR29: =$C$24 -> 2300000 | AS29: =$C$24 -> 2300000 | ... AW29: =$C$24 -> 2300000
B30: IIGG | C30: 0.05 | G30: Previsión aguinaldo | J30: =J24/12 -> 3350000 | K30: =K24/12 -> 3350000 | L30: =L24/12 -> 3350000 | M30: =M24/12 -> 3750000 | N30: =N24/12 -> 3750000 | O30: =O24/12 -> 3350000 | P30: =P24/12 -> 3350000 | Q30: =Q24/12 -> 3750000 | ... U30: =U24/12 -> 4500000 | X30: =X24/12 -> 5000000 | Y30: =Y24/12 -> 5000000 | Z30: =Z24/12 -> 5000000 | AA30: =AA24/12 -> 5000000 | AB30: =AB24/12 -> 5000000 | AC30: =AC24/12 -> 5000000 | AD30: =AD24/12 -> 5000000 | AE30: =AE24/12 -> 5000000 | ... AI30: =AI24/12 -> 5000000 | AL30: =AL24/12 -> 5000000 | AM30: =AM24/12 -> 5000000 | AN30: =AN24/12 -> 5000000 | AO30: =AO24/12 -> 5000000 | AP30: =AP24/12 -> 5000000 | AQ30: =AQ24/12 -> 5000000 | AR30: =AR24/12 -> 5000000 | AS30: =AS24/12 -> 5000000 | ... AW30: =AW24/12 -> 5000000
F31: Proveedores | G31: Dirección Operativa | J31: 5000000 | K31: 5000000 | L31: 5000000 | M31: 5000000 | N31: 5000000 | O31: 5000000 | P31: 5000000 | Q31: 5000000 | R31: 5000000 | S31: 5000000 | T31: 5000000 | U31: 5000000 | X31: 5000000 | Y31: 5000000 | Z31: 5000000 | AA31: 5000000 | AB31: 5000000 | AC31: 5000000 | AD31: 5000000 | AE31: 5000000 | AF31: 5000000 | AG31: 5000000 | AH31: 5000000 | AI31: 5000000 | AL31: 5000000 | AM31: 5000000 | AN31: 5000000 | AO31: 5000000 | AP31: 5000000 | AQ31: 5000000 | AR31: 5000000 | AS31: 5000000 | AT31: 5000000 | AU31: 5000000 | AV31: 5000000 | AW31: 5000000
B32: Fondo Despidos | C32: 0.01 | F32: Proveedores | G32: Bruno Bonnao | J32: 3886000 | K32: 3886000 | L32: 3886000 | M32: 3886000 | N32: 3886000 | O32: 3886000 | P32: 3886000 | Q32: 3886000 | R32: 3886000 | S32: 3886000 | T32: 3886000 | U32: 3886000 | X32: 3886000 | Y32: 3886000 | Z32: 3886000 | AA32: 3886000 | AB32: 3886000 | AC32: 3886000 | AD32: 3886000 | AE32: 3886000 | AF32: 3886000 | AG32: 3886000 | AH32: 3886000 | AI32: 3886000 | AL32: 3886000 | AM32: 3886000 | AN32: 3886000 | AO32: 3886000 | AP32: 3886000 | AQ32: 3886000 | AR32: 3886000 | AS32: 3886000 | AT32: 3886000 | AU32: 3886000 | AV32: 3886000 | AW32: 3886000
B34: TIR | C34: ='Cash Flow'!C16 -> 0.36776345 | F34: EBITDA | H34: ARS | J34: =J19-J23 -> -7093556.3 | K34: =K19-K23 -> 4589072.3 | L34: =L19-L23 -> 1620260.3 | M34: =M19-M23 -> 35142935 | N34: =N19-N23 -> 11124715 | O34: =O19-O23 -> -11759716 | P34: =P19-P23 -> 552901.7 | Q34: =Q19-Q23 -> 28353544 | ... U34: =U19-U23 -> 40741516 | W34: ARS | X34: =X19-X23 -> -22003334 | Y34: =Y19-Y23 -> 38889120 | Z34: =Z19-Z23 -> 33941100 | AA34: =AA19-AA23 -> 83173900 | AB34: =AB19-AB23 -> 46222793 | AC34: =AC19-AC23 -> 3015975.5 | AD34: =AD19-AD23 -> 13212431 | AE34: =AE19-AE23 -> 49633392 | ... AI34: =AI19-AI23 -> 34241516 | AK34: ARS | AL34: =AL19-AL23 -> 18427130 | AM34: =AM19-AM23 -> 26218655 | AN34: =AN19-AN23 -> 21720455 | AO34: =AO19-AO23 -> 66477545 | AP34: =AP19-AP23 -> 32885630 | AQ34: =AQ19-AQ23 -> -6393295 | AR34: =AR19-AR23 -> 2876210 | AS34: =AS19-AS23 -> 35986175 | ... AW34: =AW19-AW23 -> 21993560
B35: VAN | C35: ='Cash Flow'!C14 -> 399459.45 | H35: % | J35: =J34/J5 -> -0.050286223 | K35: =K34/K5 -> 0.027987143 | L35: =L34/L5 -> 0.010245116 | M35: =M34/M5 -> 0.1501345 | N35: =N34/N5 -> 0.059496249 | O35: =O34/O5 -> -0.089146647 | P35: =P34/P5 -> 0.0035429546 | Q35: =Q34/Q5 -> 0.12843384 | ... U35: =U34/U5 -> 0.15422368 | W35: % | X35: =X34/X5 -> -0.14298317 | Y35: =Y34/Y5 -> 0.14230267 | Z35: =Z34/Z5 -> 0.12876839 | AA35: =AA34/AA5 -> 0.23096326 | AB35: =AB34/AB5 -> 0.16068311 | AC35: =AC34/AC5 -> 0.014861045 | AD35: =AD34/AD5 -> 0.05926502 | AE35: =AE34/AE5 -> 0.16861932 | ... AI35: =AI34/AI5 -> 0.12961846 | AK35: % | AL35: =AL34/AL5 -> 0.079031107 | AM35: =AM34/AM5 -> 0.10553293 | AN35: =AN34/AN5 -> 0.090645229 | AO35: =AO34/AO5 -> 0.20305958 | AP35: =AP34/AP5 -> 0.12575142 | AQ35: =AQ34/AQ5 -> -0.034652851 | AR35: =AR34/AR5 -> 0.014191522 | AS35: =AS34/AS5 -> 0.13448125 | ... AW35: =AW34/AW5 -> 0.091580306
B37: CAPEX | C37: =-I69 -> 370000 | G37: Depreciaciones | J37: 0 | K37: 0 | L37: 0 | M37: 0 | N37: 0 | O37: 0 | P37: 0 | Q37: 0 | R37: 0 | S37: 0 | T37: 0 | U37: 0 | X37: 0 | Y37: 0 | Z37: 0 | AA37: 0 | AB37: 0 | AC37: 0 | AD37: 0 | AE37: 0 | AF37: 0 | AG37: 0 | AH37: 0 | AI37: 0 | AL37: 0 | AM37: 0 | AN37: 0 | AO37: 0 | AP37: 0 | AQ37: 0 | AR37: 0 | AS37: 0 | AT37: 0 | AU37: 0 | AV37: 0 | AW37: 0
B38: CAJA Operativa | C38: =I66 -> 61000
B39: INV. Requerida | C39: =SUM(C37:C38) -> 431000 | F39: EBIT | H39: ARS | J39: =J34-J37 -> -7093556.3 | K39: =K34-K37 -> 4589072.3 | L39: =L34-L37 -> 1620260.3 | M39: =M34-M37 -> 35142935 | N39: =N34-N37 -> 11124715 | O39: =O34-O37 -> -11759716 | P39: =P34-P37 -> 552901.7 | Q39: =Q34-Q37 -> 28353544 | ... U39: =U34-U37 -> 40741516 | W39: ARS | X39: =X34-X37 -> -22003334 | Y39: =Y34-Y37 -> 38889120 | Z39: =Z34-Z37 -> 33941100 | AA39: =AA34-AA37 -> 83173900 | AB39: =AB34-AB37 -> 46222793 | AC39: =AC34-AC37 -> 3015975.5 | AD39: =AD34-AD37 -> 13212431 | AE39: =AE34-AE37 -> 49633392 | ... AI39: =AI34-AI37 -> 34241516 | AK39: ARS | AL39: =AL34-AL37 -> 18427130 | AM39: =AM34-AM37 -> 26218655 | AN39: =AN34-AN37 -> 21720455 | AO39: =AO34-AO37 -> 66477545 | AP39: =AP34-AP37 -> 32885630 | AQ39: =AQ34-AQ37 -> -6393295 | AR39: =AR34-AR37 -> 2876210 | AS39: =AS34-AS37 -> 35986175 | ... AW39: =AW34-AW37 -> 21993560
H40: % | J40: =J39/J5 -> -0.050286223 | K40: =K39/K5 -> 0.027987143 | L40: =L39/L5 -> 0.010245116 | M40: =M39/M5 -> 0.1501345 | N40: =N39/N5 -> 0.059496249 | O40: =O39/O5 -> -0.089146647 | P40: =P39/P5 -> 0.0035429546 | Q40: =Q39/Q5 -> 0.12843384 | ... U40: =U39/U5 -> 0.15422368 | W40: % | X40: =X39/X5 -> -0.14298317 | Y40: =Y39/Y5 -> 0.14230267 | Z40: =Z39/Z5 -> 0.12876839 | AA40: =AA39/AA5 -> 0.23096326 | AB40: =AB39/AB5 -> 0.16068311 | AC40: =AC39/AC5 -> 0.014861045 | AD40: =AD39/AD5 -> 0.05926502 | AE40: =AE39/AE5 -> 0.16861932 | ... AI40: =AI39/AI5 -> 0.12961846 | AK40: % | AL40: =AL39/AL5 -> 0.079031107 | AM40: =AM39/AM5 -> 0.10553293 | AN40: =AN39/AN5 -> 0.090645229 | AO40: =AO39/AO5 -> 0.20305958 | AP40: =AP39/AP5 -> 0.12575142 | AQ40: =AQ39/AQ5 -> -0.034652851 | AR40: =AR39/AR5 -> 0.014191522 | AS40: =AS39/AS5 -> 0.13448125 | ... AW40: =AW39/AW5 -> 0.091580306
B41: WACC Año 1 | C41: ='Cash Flow'!H35 -> 0.22808944
G42: Impuestos | J42: =IF(J39>0,J39*$C$30,0) -> 0 | K42: =IF(K39>0,K39*$C$30,0) -> 229453.61 | L42: =IF(L39>0,L39*$C$30,0) -> 81013.015 | M42: =IF(M39>0,M39*$C$30,0) -> 1757146.7 | N42: =IF(N39>0,N39*$C$30,0) -> 556235.77 | O42: =IF(O39>0,O39*$C$30,0) -> 0 | P42: =IF(P39>0,P39*$C$30,0) -> 27645.085 | Q42: =IF(Q39>0,Q39*$C$30,0) -> 1417677.2 | ... U42: =IF(U39>0,U39*$C$30,0) -> 2037075.8 | X42: =IF(X39>0,X39*$C$30,0) -> 0 | Y42: =IF(Y39>0,Y39*$C$30,0) -> 1944456 | Z42: =IF(Z39>0,Z39*$C$30,0) -> 1697055 | AA42: =IF(AA39>0,AA39*$C$30,0) -> 4158695 | AB42: =IF(AB39>0,AB39*$C$30,0) -> 2311139.6 | AC42: =IF(AC39>0,AC39*$C$30,0) -> 150798.78 | AD42: =IF(AD39>0,AD39*$C$30,0) -> 660621.55 | AE42: =IF(AE39>0,AE39*$C$30,0) -> 2481669.6 | ... AI42: =IF(AI39>0,AI39*$C$30,0) -> 1712075.8 | AL42: =IF(AL39>0,AL39*$C$30,0) -> 921356.5 | AM42: =IF(AM39>0,AM39*$C$30,0) -> 1310932.8 | AN42: =IF(AN39>0,AN39*$C$30,0) -> 1086022.8 | AO42: =IF(AO39>0,AO39*$C$30,0) -> 3323877.2 | AP42: =IF(AP39>0,AP39*$C$30,0) -> 1644281.5 | AQ42: =IF(AQ39>0,AQ39*$C$30,0) -> 0 | AR42: =IF(AR39>0,AR39*$C$30,0) -> 143810.5 | AS42: =IF(AS39>0,AS39*$C$30,0) -> 1799308.8 | ... AW42: =IF(AW39>0,AW39*$C$30,0) -> 1099678
B43: Payback (meses) | C43: =_xlfn.XLOOKUP("PAYBACK",I94:AW94,I91:AW91,"+ de 36 meses") -> + de 36 meses
F44: RESULTADO NETO | H44: ARS | J44: =J39-J42 -> -7093556.3 | K44: =K39-K42 -> 4359618.7 | L44: =L39-L42 -> 1539247.3 | M44: =M39-M42 -> 33385788 | N44: =N39-N42 -> 10568480 | O44: =O39-O42 -> -11759716 | P44: =P39-P42 -> 525256.62 | Q44: =Q39-Q42 -> 26935867 | ... U44: =U39-U42 -> 38704440 | W44: ARS | X44: =X39-X42 -> -22003334 | Y44: =Y39-Y42 -> 36944664 | Z44: =Z39-Z42 -> 32244045 | AA44: =AA39-AA42 -> 79015205 | AB44: =AB39-AB42 -> 43911653 | AC44: =AC39-AC42 -> 2865176.7 | AD44: =AD39-AD42 -> 12551809 | AE44: =AE39-AE42 -> 47151723 | ... AI44: =AI39-AI42 -> 32529440 | AK44: ARS | AL44: =AL39-AL42 -> 17505774 | AM44: =AM39-AM42 -> 24907722 | AN44: =AN39-AN42 -> 20634432 | AO44: =AO39-AO42 -> 63153668 | AP44: =AP39-AP42 -> 31241348 | AQ44: =AQ39-AQ42 -> -6393295 | AR44: =AR39-AR42 -> 2732399.5 | AS44: =AS39-AS42 -> 34186866 | ... AW44: =AW39-AW42 -> 20893882
H45: % | J45: =J44/J5 -> -0.050286223 | K45: =K44/K5 -> 0.026587786 | L45: =L44/L5 -> 0.0097328603 | M45: =M44/M5 -> 0.14262778 | N45: =N44/N5 -> 0.056521437 | O45: =O44/O5 -> -0.089146647 | P45: =P44/P5 -> 0.0033658069 | Q45: =Q44/Q5 -> 0.12201215 | ... U45: =U44/U5 -> 0.14651249 | W45: % | X45: =X44/X5 -> -0.14298317 | Y45: =Y44/Y5 -> 0.13518753 | Z45: =Z44/Z5 -> 0.12232997 | AA45: =AA44/AA5 -> 0.2194151 | AB45: =AB44/AB5 -> 0.15264895 | AC45: =AC44/AC5 -> 0.014117993 | AD45: =AD44/AD5 -> 0.056301769 | AE45: =AE44/AE5 -> 0.16018836 | ... AI45: =AI44/AI5 -> 0.12313754 | AK45: % | AL45: =AL44/AL5 -> 0.075079552 | AM45: =AM44/AM5 -> 0.10025629 | AN45: =AN44/AN5 -> 0.086112967 | AO45: =AO44/AO5 -> 0.1929066 | AP45: =AP44/AP5 -> 0.11946385 | AQ45: =AQ44/AQ5 -> -0.034652851 | AR45: =AR44/AR5 -> 0.013481946 | AS45: =AS44/AS5 -> 0.12775719 | ... AW45: =AW44/AW5 -> 0.087001291
G50: Reserva para despidos | J50: =J5*$C$32 -> 1410636.2 | K50: =K5*$C$32 -> 1639707.3 | L50: =L5*$C$32 -> 1581495.3 | M50: =M5*$C$32 -> 2340763.4 | N50: =N5*$C$32 -> 1869817.9 | O50: =O5*$C$32 -> 1319142.8 | P50: =P5*$C$32 -> 1560566.7 | Q50: =Q5*$C$32 -> 2207638.1 | ... U50: =U5*$C$32 -> 2641716 | X50: =X5*$C$32 -> 1538875.8 | Y50: =Y5*$C$32 -> 2732845.5 | Z50: =Z5*$C$32 -> 2635825.5 | AA50: =AA5*$C$32 -> 3601174.5 | AB50: =AB5*$C$32 -> 2876643 | AC50: =AC5*$C$32 -> 2029450.5 | AD50: =AD5*$C$32 -> 2229381 | AE50: =AE5*$C$32 -> 2943517.5 | ... AI50: =AI5*$C$32 -> 2641716 | AL50: =AL5*$C$32 -> 2331630 | AM50: =AM5*$C$32 -> 2484405 | AN50: =AN5*$C$32 -> 2396205 | AO50: =AO5*$C$32 -> 3273795 | AP50: =AP5*$C$32 -> 2615130 | AQ50: =AQ5*$C$32 -> 1844955 | AR50: =AR5*$C$32 -> 2026710 | AS50: =AS5*$C$32 -> 2675925 | ... AW50: =AW5*$C$32 -> 2401560
F52: INPUTS PARA NOF
G53: Caja Necesaria
G54: Clientes
G55: Proveedores | J55: =SUMIF($F$11:$F$33,"Proveedores",J11:J33) -> 1.2929017e+08 | K55: =SUMIF($F$11:$F$33,"Proveedores",K11:K33) -> 1.3799488e+08 | L55: =SUMIF($F$11:$F$33,"Proveedores",L11:L33) -> 1.3578282e+08 | M55: =SUMIF($F$11:$F$33,"Proveedores",M11:M33) -> 1.6943501e+08 | N55: =SUMIF($F$11:$F$33,"Proveedores",N11:N33) -> 1.5153908e+08 | O55: =SUMIF($F$11:$F$33,"Proveedores",O11:O33) -> 1.2581343e+08 | P55: =SUMIF($F$11:$F$33,"Proveedores",P11:P33) -> 1.3498753e+08 | Q55: =SUMIF($F$11:$F$33,"Proveedores",Q11:Q33) -> 1.6437625e+08 | ... U55: =SUMIF($F$11:$F$33,"Proveedores",U11:U33) -> 1.8987121e+08 | X55: =SUMIF($F$11:$F$33,"Proveedores",X11:X33) -> 1.5396328e+08 | Y55: =SUMIF($F$11:$F$33,"Proveedores",Y11:Y33) -> 199334129 | Z55: =SUMIF($F$11:$F$33,"Proveedores",Z11:Z33) -> 195647369 | AA55: =SUMIF($F$11:$F$33,"Proveedores",AA11:AA33) -> 2.3233063e+08 | AB55: =SUMIF($F$11:$F$33,"Proveedores",AB11:AB33) -> 204798434 | AC55: =SUMIF($F$11:$F$33,"Proveedores",AC11:AC33) -> 172605119 | AD55: =SUMIF($F$11:$F$33,"Proveedores",AD11:AD33) -> 180202478 | AE55: =SUMIF($F$11:$F$33,"Proveedores",AE11:AE33) -> 207339665 | ... AI55: =SUMIF($F$11:$F$33,"Proveedores",AI11:AI33) -> 1.9587121e+08 | AL55: =SUMIF($F$11:$F$33,"Proveedores",AL11:AL33) -> 184087940 | AM55: =SUMIF($F$11:$F$33,"Proveedores",AM11:AM33) -> 189893390 | AN55: =SUMIF($F$11:$F$33,"Proveedores",AN11:AN33) -> 186541790 | AO55: =SUMIF($F$11:$F$33,"Proveedores",AO11:AO33) -> 219890210 | AP55: =SUMIF($F$11:$F$33,"Proveedores",AP11:AP33) -> 194860940 | AQ55: =SUMIF($F$11:$F$33,"Proveedores",AQ11:AQ33) -> 165594290 | AR55: =SUMIF($F$11:$F$33,"Proveedores",AR11:AR33) -> 172500980 | AS55: =SUMIF($F$11:$F$33,"Proveedores",AS11:AS33) -> 197171150 | ... AW55: =SUMIF($F$11:$F$33,"Proveedores",AW11:AW33) -> 186745280
H57: TC | J57: 1420 | K57: 1420 | L57: 1420 | M57: 1420 | N57: 1420 | O57: 1420 | P57: 1420 | Q57: 1420 | R57: 1420 | S57: 1420 | T57: 1420 | U57: 1420 | X57: 1420 | Y57: 1420 | Z57: 1420 | AA57: 1420 | AB57: 1420 | AC57: 1420 | AD57: 1420 | AE57: 1420 | AF57: 1420 | AG57: 1420 | AH57: 1420 | AI57: 1420 | AL57: 1420 | AM57: 1420 | AN57: 1420 | AO57: 1420 | AP57: 1420 | AQ57: 1420 | AR57: 1420 | AS57: 1420 | AT57: 1420 | AU57: 1420 | AV57: 1420 | AW57: 1420
J58: AÑO 1 | X58: AÑO 1 | AL58: AÑO 1
J59: 1 | K59: 2 | L59: 3 | M59: 4 | N59: 5 | O59: 6 | P59: 7 | Q59: 8 | R59: 9 | S59: 10 | T59: 11 | U59: 12 | X59: 1 | Y59: 2 | Z59: 3 | AA59: 4 | AB59: 5 | AC59: 6 | AD59: 7 | AE59: 8 | AF59: 9 | AG59: 10 | AH59: 11 | AI59: 12 | AL59: 1 | AM59: 2 | AN59: 3 | AO59: 4 | AP59: 5 | AQ59: 6 | AR59: 7 | AS59: 8 | AT59: 9 | AU59: 10 | AV59: 11 | AW59: 12
I60: Dias del mes | J60: 31 | K60: 30 | L60: 31 | M60: 30 | N60: 31 | O60: 31 | P60: 28 | Q60: 31 | R60: 30 | S60: 31 | T60: 30 | U60: 31 | X60: 31 | Y60: 30 | Z60: 31 | AA60: 30 | AB60: 31 | AC60: 31 | AD60: 28 | AE60: 31 | AF60: 30 | AG60: 31 | AH60: 30 | AI60: 31 | AL60: 31 | AM60: 30 | AN60: 31 | AO60: 30 | AP60: 31 | AQ60: 31 | AR60: 28 | AS60: 31 | AT60: 30 | AU60: 31 | AV60: 30 | AW60: 31
F61: Cash Flow | H61: Unidad | J61: Ago | K61: Sep | L61: Oct | M61: Nov | N61: Dic | O61: Ene | P61: Feb | Q61: Mar | R61: Abr | S61: May | T61: Jun | U61: Jul | X61: Ago | Y61: Sep | Z61: Oct | AA61: Nov | AB61: Dic | AC61: Ene | AD61: Feb | AE61: Mar | AF61: Abr | AG61: May | AH61: Jun | AI61: Jul | AL61: Ago | AM61: Sep | AN61: Oct | AO61: Nov | AP61: Dic | AQ61: Ene | AR61: Feb | AS61: Mar | AT61: Abr | AU61: May | AV61: Jun | AW61: Jul
F62: NOPAT | H62: USD | J62: =J44/J57 -> -4995.4622 | K62: =K44/K57 -> 3070.154 | L62: =L44/L57 -> 1083.977 | M62: =M44/M57 -> 23511.118 | N62: =N44/N57 -> 7442.5913 | O62: =O44/O57 -> -8281.4901 | P62: =P44/P57 -> 369.89902 | Q62: =Q44/Q57 -> 18968.921 | ... U62: =U44/U57 -> 27256.648 | X62: =X44/X57 -> -15495.306 | Y62: =Y44/Y57 -> 26017.369 | Z62: =Z44/Z57 -> 22707.074 | AA62: =AA44/AA57 -> 55644.51 | AB62: =AB44/AB57 -> 30923.7 | AC62: =AC44/AC57 -> 2017.7301 | AD62: =AD44/AD57 -> 8839.3024 | AE62: =AE44/AE57 -> 33205.439 | ... AI62: =AI44/AI57 -> 22908.056 | AL62: =AL44/AL57 -> 12328.01 | AM62: =AM44/AM57 -> 17540.649 | AN62: =AN44/AN57 -> 14531.29 | AO62: =AO44/AO57 -> 44474.414 | AP62: =AP44/AP57 -> 22000.95 | AQ62: =AQ44/AQ57 -> -4502.3204 | AR62: =AR44/AR57 -> 1924.225 | AS62: =AS44/AS57 -> 24075.258 | ... AW62: =AW44/AW57 -> 14714.001
F63: +DA | H63: USD | I63: =J37 -> 0 | J63: =J37 -> 0 | K63: =K37 -> 0 | L63: =L37 -> 0 | M63: =M37 -> 0 | N63: =N37 -> 0 | O63: =O37 -> 0 | P63: =P37 -> 0 | Q63: =Q37 -> 0 | ... U63: =U37 -> 0 | X63: =X37 -> 0 | Y63: =Y37 -> 0 | Z63: =Z37 -> 0 | AA63: =AA37 -> 0 | AB63: =AB37 -> 0 | AC63: =AC37 -> 0 | AD63: =AD37 -> 0 | AE63: =AE37 -> 0 | ... AI63: =AI37 -> 0 | AL63: =AL37 -> 0 | AM63: =AM37 -> 0 | AN63: =AN37 -> 0 | AO63: =AO37 -> 0 | AP63: =AP37 -> 0 | AQ63: =AQ37 -> 0 | AR63: =AR37 -> 0 | AS63: =AS37 -> 0 | ... AW63: =AW37 -> 0
F64: +Delta NOF | H64: USD | I64: =-I65 -> -61000 | J64: =-J65+I65 -> 60192.685 | K64: =-K65+J65 -> -4490.0338 | L64: =-L65+K65 -> 1268.4733 | M64: =-M65+L65 -> -13237.407 | N64: =-N65+M65 -> 9436.6848 | O64: =-O65+N65 -> 8747.3956 | P64: =-P65+O65 -> -4941.4486 | Q64: =-Q65+P65 -> -10175.569 | ... U64: =-U65+T65 -> -9433.3336 | X64: =-X65+U65 -> 22838.65 | Y64: =-Y65+X65 -> -23145.402 | Z64: =-Z65+Y65 -> 2462.3427 | AA64: =-AA65+Z65 -> -19380.49 | AB64: =-AB65+AA65 -> 14839.86 | AC64: =-AC65+AB65 -> 15973.87 | AD64: =-AD65+AC65 -> -4787.3317 | AE64: =-AE65+AD65 -> -12447.462 | AF64: =-AF65+AE65 -> -839.69364 | ... AI64: =-AI65+AH65 -> -8423.409 | AL64: =-AL65+AI65 -> 5846.692 | AM64: =-AM65+AL65 -> -3357.4615 | AN64: =-AN65+AM65 -> 2139.8956 | AO64: =-AO65+AN65 -> -17520.029 | AP64: =-AP65+AO65 -> 13392.184 | AQ64: =-AQ65+AP65 -> 14521.7 | AR64: =-AR65+AQ65 -> -4035.1984 | AS64: =-AS65+AR65 -> -11632.796 | AT64: =-AT65+AS65 -> -664.76011 | ... AW64: =-AW65+AV65 -> -7756.2423
F65: -Inversión en NOF | H65: USD | I65: =(I66+I67)-I68 -> 61000 | J65: =(J66+J67)-J68 -> 807.31496 | K65: =K66+K67-K68 -> 5297.3488 | L65: =L66+L67-L68 -> 4028.8755 | M65: =M66+M67-M68 -> 17266.283 | N65: =N66+N67-N68 -> 7829.5979 | O65: =O66+O67-O68 -> -917.79771 | P65: =P66+P67-P68 -> 4023.6509 | Q65: =Q66+Q67-Q68 -> 14199.22 | R65: =R66+R67-R68 -> 17599.447 | ... U65: =U66+U67-U68 -> 19316.999 | X65: =(X66+X67)-X68 -> -3521.6512 | Y65: =Y66+Y67-Y68 -> 19623.75 | Z65: =Z66+Z67-Z68 -> 17161.408 | AA65: =AA66+AA67-AA68 -> 36541.898 | AB65: =AB66+AB67-AB68 -> 21702.037 | AC65: =AC66+AC67-AC68 -> 5728.1671 | AD65: =AD66+AD67-AD68 -> 10515.499 | AE65: =AE66+AE67-AE68 -> 22962.961 | AF65: =AF66+AF67-AF68 -> 23802.654 | ... AI65: =AI66+AI67-AI68 -> 17272.473 | AL65: =(AL66+AL67)-AL68 -> 11425.781 | AM65: =AM66+AM67-AM68 -> 14783.243 | AN65: =AN66+AN67-AN68 -> 12643.347 | AO65: =AO66+AO67-AO68 -> 30163.377 | AP65: =AP66+AP67-AP68 -> 16771.193 | AQ65: =AQ66+AQ67-AQ68 -> 2249.4923 | AR65: =AR66+AR67-AR68 -> 6284.6906 | AS65: =AS66+AS67-AS68 -> 17917.486 | AT65: =AT66+AT67-AT68 -> 18582.246 | ... AW65: =AW66+AW67-AW68 -> 12744.316
F66: 4 | G66: Caja necesaria | H66: Dias | I66: 61000 | J66: =((J5/J60)*$F$66)/J57 -> 12818.139 | K66: =((K5/K60)*$F$66)/K57 -> 15396.313 | L66: =((L5/L60)*$F$66)/L57 -> 14370.698 | M66: =((M5/M60)*$F$66)/M57 -> 21978.999 | N66: =((N5/N60)*$F$66)/N57 -> 16990.622 | O66: =((O5/O60)*$F$66)/O57 -> 11986.759 | P66: =((P5/P60)*$F$66)/P57 -> 15699.866 | Q66: =((Q5/Q60)*$F$66)/Q57 -> 20060.319 | ... U66: =((U5/U60)*$F$66)/U57 -> 24004.689 | X66: =((X5/X60)*$F$66)/X57 -> 13983.424 | Y66: =((Y5/Y60)*$F$66)/Y57 -> 25660.521 | Z66: =((Z5/Z60)*$F$66)/Z57 -> 23951.163 | AA66: =((AA5/AA60)*$F$66)/AA57 -> 33813.845 | AB66: =((AB5/AB60)*$F$66)/AB57 -> 26139.418 | AC66: =((AC5/AC60)*$F$66)/AC57 -> 18441.168 | AD66: =((AD5/AD60)*$F$66)/AD57 -> 22428.38 | AE66: =((AE5/AE60)*$F$66)/AE57 -> 26747.092 | ... AI66: =((AI5/AI60)*$F$66)/AI57 -> 24004.689 | AL66: =((AL5/AL60)*$F$66)/AL57 -> 21187.006 | AM66: =((AM5/AM60)*$F$66)/AM57 -> 23327.746 | AN66: =((AN5/AN60)*$F$66)/AN57 -> 21773.785 | AO66: =((AO5/AO60)*$F$66)/AO57 -> 30739.859 | AP66: =((AP5/AP60)*$F$66)/AP57 -> 23763.108 | AQ66: =((AQ5/AQ60)*$F$66)/AQ57 -> 16764.698 | AR66: =((AR5/AR60)*$F$66)/AR57 -> 20389.437 | AS66: =((AS5/AS60)*$F$66)/AS57 -> 24315.538 | ... AW66: =((AW5/AW60)*$F$66)/AW57 -> 21822.444
F67: 10 | G67: Clientes | H67: Dias | I67: 0 | J67: =((J5/J60)*$F$67)/J57 -> 32045.346 | K67: =((K5/K60)*$F$67)/K57 -> 38490.782 | L67: =((L5/L60)*$F$67)/L57 -> 35926.745 | M67: =((M5/M60)*$F$67)/M57 -> 54947.498 | N67: =((N5/N60)*$F$67)/N57 -> 42476.555 | O67: =((O5/O60)*$F$67)/O57 -> 29966.897 | P67: =((P5/P60)*$F$67)/P57 -> 39249.665 | Q67: =((Q5/Q60)*$F$67)/Q57 -> 50150.798 | ... U67: =((U5/U60)*$F$67)/U57 -> 60011.722 | X67: =((X5/X60)*$F$67)/X57 -> 34958.56 | Y67: =((Y5/Y60)*$F$67)/Y57 -> 64151.303 | Z67: =((Z5/Z60)*$F$67)/Z57 -> 59877.908 | AA67: =((AA5/AA60)*$F$67)/AA57 -> 84534.613 | AB67: =((AB5/AB60)*$F$67)/AB57 -> 65348.546 | AC67: =((AC5/AC60)*$F$67)/AC57 -> 46102.919 | AD67: =((AD5/AD60)*$F$67)/AD57 -> 56070.951 | AE67: =((AE5/AE60)*$F$67)/AE57 -> 66867.731 | ... AI67: =((AI5/AI60)*$F$67)/AI57 -> 60011.722 | AL67: =((AL5/AL60)*$F$67)/AL57 -> 52967.515 | AM67: =((AM5/AM60)*$F$67)/AM57 -> 58319.366 | AN67: =((AN5/AN60)*$F$67)/AN57 -> 54434.462 | AO67: =((AO5/AO60)*$F$67)/AO57 -> 76849.648 | AP67: =((AP5/AP60)*$F$67)/AP57 -> 59407.769 | AQ67: =((AQ5/AQ60)*$F$67)/AQ57 -> 41911.745 | AR67: =((AR5/AR60)*$F$67)/AR57 -> 50973.592 | AS67: =((AS5/AS60)*$F$67)/AS57 -> 60788.846 | ... AW67: =((AW5/AW60)*$F$67)/AW57 -> 54556.111
F68: 15 | G68: Proveedores | H68: Dias | J68: =((J55/J60)*$F$68)/J57 -> 44056.17 | K68: =((K55/K60)*$F$68)/K57 -> 48589.746 | L68: =((L55/L60)*$F$68)/L57 -> 46268.567 | M68: =((M55/M60)*$F$68)/M57 -> 59660.215 | N68: =((N55/N60)*$F$68)/N57 -> 51637.579 | O68: =((O55/O60)*$F$68)/O57 -> 42871.454 | P68: =((P55/P60)*$F$68)/P57 -> 50925.881 | Q68: =((Q55/Q60)*$F$68)/Q57 -> 56011.898 | ... U68: =((U55/U60)*$F$68)/U57 -> 64699.412 | X68: =((X55/X60)*$F$68)/X57 -> 52463.635 | Y68: =((Y55/Y60)*$F$68)/Y57 -> 70188.074 | Z68: =((Z55/Z60)*$F$68)/Z57 -> 66667.663 | AA68: =((AA55/AA60)*$F$68)/AA57 -> 81806.56 | AB68: =((AB55/AB60)*$F$68)/AB57 -> 69785.927 | AC68: =((AC55/AC60)*$F$68)/AC57 -> 58815.92 | AD68: =((AD55/AD60)*$F$68)/AD57 -> 67983.832 | AE68: =((AE55/AE60)*$F$68)/AE57 -> 70651.862 | ... AI68: =((AI55/AI60)*$F$68)/AI57 -> 66743.937 | AL68: =((AL55/AL60)*$F$68)/AL57 -> 62728.739 | AM68: =((AM55/AM60)*$F$68)/AM57 -> 66863.87 | AN68: =((AN55/AN60)*$F$68)/AN57 -> 63564.899 | AO68: =((AO55/AO60)*$F$68)/AO57 -> 77426.13 | AP68: =((AP55/AP60)*$F$68)/AP57 -> 66399.684 | AQ68: =((AQ55/AQ60)*$F$68)/AQ57 -> 56426.95 | AR68: =((AR55/AR60)*$F$68)/AR57 -> 65078.338 | AS68: =((AS55/AS60)*$F$68)/AS57 -> 67186.898 | ... AW68: =((AW55/AW60)*$F$68)/AW57 -> 63634.239
F69: -CAPEX | H69: USD | I69: -370000
F70: -Otros A&P operativos (reserva para despidos) Chequear si va DELTA
G71: Prevision Aguinaldo | J71: =-J30/J57 -> -2359.1549 | K71: =-K30/K57 -> -2359.1549 | L71: =-L30/L57 -> -2359.1549 | M71: =-M30/M57 -> -2640.8451 | N71: =-N30/N57 -> -2640.8451 | O71: =-O30/O57 -> -2359.1549 | P71: =-P30/P57 -> -2359.1549 | Q71: =-Q30/Q57 -> -2640.8451 | ... U71: =-U30/U57 -> -3169.0141 | X71: =-X30/X57 -> -3521.1268 | Y71: =-Y30/Y57 -> -3521.1268 | Z71: =-Z30/Z57 -> -3521.1268 | AA71: =-AA30/AA57 -> -3521.1268 | AB71: =-AB30/AB57 -> -3521.1268 | AC71: =-AC30/AC57 -> -3521.1268 | AD71: =-AD30/AD57 -> -3521.1268 | AE71: =-AE30/AE57 -> -3521.1268 | ... AI71: =-AI30/AI57 -> -3521.1268 | AL71: =-AL30/AL57 -> -3521.1268 | AM71: =-AM30/AM57 -> -3521.1268 | AN71: =-AN30/AN57 -> -3521.1268 | AO71: =-AO30/AO57 -> -3521.1268 | AP71: =-AP30/AP57 -> -3521.1268 | AQ71: =-AQ30/AQ57 -> -3521.1268 | AR71: =-AR30/AR57 -> -3521.1268 | AS71: =-AS30/AS57 -> -3521.1268 | ... AW71: =-AW30/AW57 -> -3521.1268
G72: Prevision Impuestos | J72: =J42/J57 -> 0 | K72: =K42/K57 -> 161.58705 | L72: =L42/L57 -> 57.051419 | M72: =-M42/M57 -> -1237.4273 | N72: =-N42/N57 -> -391.71533 | O72: =-O42/O57 -> 0 | P72: =-P42/P57 -> -19.46837 | Q72: =-Q42/Q57 -> -998.36424 | R72: =-R42/R57 -> -1268.1346 | S72: =-S42/S57 -> -1339.194 | T72: =-T42/T57 -> -556.98119 | U72: =-U42/U57 -> -1434.5604 | X72: =X42/X57 -> 0 | Y72: =Y42/Y57 -> 1369.3352 | Z72: =Z42/Z57 -> 1195.1092 | AA72: =-AA42/AA57 -> -2928.6584 | AB72: =-AB42/AB57 -> -1627.5631 | AC72: =-AC42/AC57 -> -106.19632 | AD72: =-AD42/AD57 -> -465.22644 | AE72: =-AE42/AE57 -> -1747.6547 | AF72: =-AF42/AF57 -> -1754.4993 | AG72: =-AG42/AG57 -> -1526.7609 | AH72: =-AH42/AH57 -> -376.24671 | AI72: =-AI42/AI57 -> -1205.6872 | AL72: =AL42/AL57 -> 648.84261 | AM72: =AM42/AM57 -> 923.19208 | AN72: =AN42/AN57 -> 764.80475 | AO72: =-AO42/AO57 -> -2340.7586 | AP72: =-AP42/AP57 -> -1157.9447 | AQ72: =-AQ42/AQ57 -> 0 | AR72: =-AR42/AR57 -> -101.275 | AS72: =-AS42/AS57 -> -1267.1188 | AT72: =-AT42/AT57 -> -1273.3412 | AU72: =-AU42/AU57 -> -1066.3063 | AV72: =-AV42/AV57 -> -20.384331 | AW72: =-AW42/AW57 -> -774.42113
G73: Reserva para Desp | H73: USD | J73: =-J50/J57 -> -993.40574 | K73: =-K50/K57 -> -1154.7235 | L73: =K73 -> -1154.7235 | M73: =L73 -> -1154.7235 | N73: =M73 -> -1154.7235 | O73: =N73 -> -1154.7235 | P73: =O73 -> -1154.7235 | Q73: =P73 -> -1154.7235 | R73: =Q73 -> -1154.7235 | S73: =R73 -> -1154.7235 | ... U73: =T73 -> -1154.7235 | X73: =-X50/X57 -> -1083.7154 | Y73: =-Y50/Y57 -> -1924.5391 | Z73: =Y73 -> -1924.5391 | AA73: =Z73 -> -1924.5391 | AB73: =AA73 -> -1924.5391 | AC73: =AB73 -> -1924.5391 | AD73: =AC73 -> -1924.5391 | AE73: =AD73 -> -1924.5391 | AF73: =AE73 -> -1924.5391 | AG73: =AF73 -> -1924.5391 | ... AI73: =AH73 -> -1924.5391 | AL73: =-AL50/AL57 -> -1641.993 | AM73: =-AM50/AM57 -> -1749.581 | AN73: =AM73 -> -1749.581 | AO73: =AN73 -> -1749.581 | AP73: =AO73 -> -1749.581 | AQ73: =AP73 -> -1749.581 | AR73: =AQ73 -> -1749.581 | AS73: =AR73 -> -1749.581 | AT73: =AS73 -> -1749.581 | AU73: =AT73 -> -1749.581 | ... AW73: =AV73 -> -1749.581
F74: FFL | H74: USD | I74: =I62+I63+I64+I69 -> -431000 | J74: =J62+J63+J64+J69+J71+J72+J73 -> 51844.662 | K74: =K62+K63+K64+K69+K71+K72+K73 -> -4772.1712 | L74: =L62+L63+L64+L69+L71+L72+L73 -> -1104.3767 | M74: =M62+M63+M64+M69+M71+M72+M73 -> 5240.7153 | N74: =N62+N63+N64+N69+N71+N72+N73 -> 12691.992 | O74: =O62+O63+O64+O69+O71+O72+O73 -> -3047.9729 | P74: =P62+P63+P64+P69+P71+P72+P73 -> -8104.8964 | Q74: =Q62+Q63+Q64+Q69+Q71+Q72+Q73 -> 3999.4192 | ... U74: =U62+U63+U64+U69+U71+U72+U73 -> 12065.016 | X74: =X62+X63+X64+X69+X71+X72+X73 -> 2738.502 | Y74: =Y62+Y63+Y64+Y69+Y71+Y72+Y73 -> -1204.3628 | Z74: =Z62+Z63+Z64+Z69+Z71+Z72+Z73 -> 20918.86 | AA74: =AA62+AA63+AA64+AA69+AA71+AA72+AA73 -> 27889.696 | AB74: =AB62+AB63+AB64+AB69+AB71+AB72+AB73 -> 38690.331 | AC74: =AC62+AC63+AC64+AC69+AC71+AC72+AC73 -> 12439.738 | AD74: =AD62+AD63+AD64+AD69+AD71+AD72+AD73 -> -1858.9215 | AE74: =AE62+AE63+AE64+AE69+AE71+AE72+AE73 -> 13564.656 | ... AI74: =AI62+AI63+AI64+AI69+AI71+AI72+AI73 -> 7833.2945 | AL74: =AL62+AL63+AL64+AL69+AL71+AL72+AL73 -> 13660.424 | AM74: =AM62+AM63+AM64+AM69+AM71+AM72+AM73 -> 9835.6723 | AN74: =AN62+AN63+AN64+AN69+AN71+AN72+AN73 -> 12165.283 | AO74: =AO62+AO63+AO64+AO69+AO71+AO72+AO73 -> 19342.918 | AP74: =AP62+AP63+AP64+AP69+AP71+AP72+AP73 -> 28964.481 | AQ74: =AQ62+AQ63+AQ64+AQ69+AQ71+AQ72+AQ73 -> 4748.6722 | AR74: =AR62+AR63+AR64+AR69+AR71+AR72+AR73 -> -7482.9561 | AS74: =AS62+AS63+AS64+AS69+AS71+AS72+AS73 -> 5904.6356 | ... AW74: =AW62+AW63+AW64+AW69+AW71+AW72+AW73 -> 912.63026
F77: Caja Acumulada | J77: 0 | K77: =J82 -> 51844.662 | L77: =K82 -> 47072.491 | M77: =L82 -> 45968.114 | N77: =M82 -> 51208.83 | O77: =N82 -> 63900.822 | P77: =O82 -> 60852.849 | Q77: =P82 -> 52747.953 | R77: =Q82 -> 56747.372 | ... U77: =T82 -> 106633.8 | X77: =U82 -> 12065.016 | Y77: =X82 -> 14803.518 | Z77: =Y82 -> 13599.156 | AA77: =Z82 -> 34518.016 | AB77: =AA82 -> 62407.712 | AC77: =AB82 -> 101098.04 | AD77: =AC82 -> 113537.78 | AE77: =AD82 -> 111678.86 | AF77: =AE82 -> 125243.52 | ... AI77: =AH82 -> 188855.54 | AL77: =AI82 -> 7833.2945 | AM77: =AL82 -> 21493.719 | AN77: =AM82 -> 31329.391 | AO77: =AN82 -> 43494.674 | AP77: =AO82 -> 19342.918 | AQ77: =AP82 -> 48307.399 | AR77: =AQ82 -> 53056.072 | AS77: =AR82 -> 45573.116 | AT77: =AS82 -> 5904.6356 | ... AW77: =AV82 -> 45502.498
F78: Requerimientos para cubrir deficit | J78: =IF(J74<0,J74,0) -> 0 | K78: =IF(K74<0,K74,0) -> -4772.1712 | L78: =IF(L74<0,L74,0) -> -1104.3767 | M78: =IF(M74<0,M74,0) -> 0 | N78: =IF(N74<0,N74,0) -> 0 | O78: =IF(O74<0,O74,0) -> -3047.9729 | P78: =IF(P74<0,P74,0) -> -8104.8964 | Q78: =IF(Q74<0,Q74,0) -> 0 | ... U78: =IF(U74<0,U74,0) -> 0 | X78: =IF(X74<0,X74,0) -> 0 | Y78: =IF(Y74<0,Y74,0) -> -1204.3628 | Z78: =IF(Z74<0,Z74,0) -> 0 | AA78: =IF(AA74<0,AA74,0) -> 0 | AB78: =IF(AB74<0,AB74,0) -> 0 | AC78: =IF(AC74<0,AC74,0) -> 0 | AD78: =IF(AD74<0,AD74,0) -> -1858.9215 | AE78: =IF(AE74<0,AE74,0) -> 0 | ... AI78: =IF(AI74<0,AI74,0) -> 0 | AL78: =IF(AL74<0,AL74,0) -> 0 | AM78: =IF(AM74<0,AM74,0) -> 0 | AN78: =IF(AN74<0,AN74,0) -> 0 | AO78: =IF(AO74<0,AO74,0) -> 0 | AP78: =IF(AP74<0,AP74,0) -> 0 | AQ78: =IF(AQ74<0,AQ74,0) -> 0 | AR78: =IF(AR74<0,AR74,0) -> -7482.9561 | AS78: =IF(AS74<0,AS74,0) -> 0 | ... AW78: =IF(AW74<0,AW74,0) -> 0
F79: Excedente de caja disponible | J79: =J74+J77 -> 51844.662 | K79: =K74+K77 -> 47072.491 | L79: =L74+L77 -> 45968.114 | M79: =M74+M77 -> 51208.83 | N79: =N74+N77 -> 63900.822 | O79: =O74+O77 -> 60852.849 | P79: =P74+P77 -> 52747.953 | Q79: =Q74+Q77 -> 56747.372 | ... U79: =U74+U77 -> 118698.81 | X79: =X74+X77 -> 14803.518 | Y79: =Y74+Y77 -> 13599.156 | Z79: =Z74+Z77 -> 34518.016 | AA79: =AA74+AA77 -> 62407.712 | AB79: =AB74+AB77 -> 101098.04 | AC79: =AC74+AC77 -> 113537.78 | AD79: =AD74+AD77 -> 111678.86 | AE79: =AE74+AE77 -> 125243.52 | ... AI79: =AI74+AI77 -> 196688.83 | AL79: =AL74+AL77 -> 21493.719 | AM79: =AM74+AM77 -> 31329.391 | AN79: =AN74+AN77 -> 43494.674 | AO79: =AO74+AO77 -> 62837.592 | AP79: =AP74+AP77 -> 48307.399 | AQ79: =AQ74+AQ77 -> 53056.072 | AR79: =AR74+AR77 -> 45573.116 | AS79: =AS74+AS77 -> 51477.751 | ... AW79: =AW74+AW77 -> 46415.129
F80: APORTES NECESARIOS | J80: =IF(J79<0,-J79,0) -> 0 | K80: =IF(K79<0,-K79,0) -> 0 | L80: =IF(L79<0,-L79,0) -> 0 | M80: =IF(M79<0,-M79,0) -> 0 | N80: =IF(N79<0,-N79,0) -> 0 | O80: =IF(O79<0,-O79,0) -> 0 | P80: =IF(P79<0,-P79,0) -> 0 | Q80: =IF(Q79<0,-Q79,0) -> 0 | ... U80: =IF(U79<0,-U79,0) -> 0 | X80: =IF(X79<0,-X79,0) -> 0 | Y80: =IF(Y79<0,-Y79,0) -> 0 | Z80: =IF(Z79<0,-Z79,0) -> 0 | AA80: =IF(AA79<0,-AA79,0) -> 0 | AB80: =IF(AB79<0,-AB79,0) -> 0 | AC80: =IF(AC79<0,-AC79,0) -> 0 | AD80: =IF(AD79<0,-AD79,0) -> 0 | AE80: =IF(AE79<0,-AE79,0) -> 0 | ... AI80: =IF(AI79<0,-AI79,0) -> 0 | AL80: =IF(AL79<0,-AL79,0) -> 0 | AM80: =IF(AM79<0,-AM79,0) -> 0 | AN80: =IF(AN79<0,-AN79,0) -> 0 | AO80: =IF(AO79<0,-AO79,0) -> 0 | AP80: =IF(AP79<0,-AP79,0) -> 0 | AQ80: =IF(AQ79<0,-AQ79,0) -> 0 | AR80: =IF(AR79<0,-AR79,0) -> 0 | AS80: =IF(AS79<0,-AS79,0) -> 0 | ... AW80: =IF(AW79<0,-AW79,0) -> 0
F81: Se Reparte Dividendos este mes? | J81: NO | K81: NO | L81: NO | M81: No | N81: NO | O81: NO | P81: NO | Q81: NO | R81: NO | S81: NO | T81: NO | U81: Si | X81: NO | Y81: NO | Z81: NO | AA81: NO | AB81: NO | AC81: NO | AD81: NO | AE81: NO | AF81: NO | AG81: NO | AH81: NO | AI81: Si | AL81: NO | AM81: NO | AN81: NO | AO81: Si | AP81: NO | AQ81: NO | AR81: NO | AS81: Si | AT81: NO | AU81: NO | AV81: NO | AW81: Si
F82: Excedente de caja retenido | J82: =IF(J81="NO",J79+J80,J74) -> 51844.662 | K82: =IF(K81="NO",K79+K80,K74) -> 47072.491 | L82: =IF(L81="NO",L79+L80,L74) -> 45968.114 | M82: =IF(M81="NO",M79+M80,M74) -> 51208.83 | N82: =IF(N81="NO",N79+N80,N74) -> 63900.822 | O82: =IF(O81="NO",O79+O80,O74) -> 60852.849 | P82: =IF(P81="NO",P79+P80,P74) -> 52747.953 | Q82: =IF(Q81="NO",Q79+Q80,Q74) -> 56747.372 | ... U82: =IF(U81="NO",U79+U80,U74) -> 12065.016 | X82: =IF(X81="NO",X79+X80,X74) -> 14803.518 | Y82: =IF(Y81="NO",Y79+Y80,Y74) -> 13599.156 | Z82: =IF(Z81="NO",Z79+Z80,Z74) -> 34518.016 | AA82: =IF(AA81="NO",AA79+AA80,AA74) -> 62407.712 | AB82: =IF(AB81="NO",AB79+AB80,AB74) -> 101098.04 | AC82: =IF(AC81="NO",AC79+AC80,AC74) -> 113537.78 | AD82: =IF(AD81="NO",AD79+AD80,AD74) -> 111678.86 | AE82: =IF(AE81="NO",AE79+AE80,AE74) -> 125243.52 | ... AI82: =IF(AI81="NO",AI79+AI80,AI74) -> 7833.2945 | AL82: =IF(AL81="NO",AL79+AL80,AL74) -> 21493.719 | AM82: =IF(AM81="NO",AM79+AM80,AM74) -> 31329.391 | AN82: =IF(AN81="NO",AN79+AN80,AN74) -> 43494.674 | AO82: =IF(AO81="NO",AO79+AO80,AO74) -> 19342.918 | AP82: =IF(AP81="NO",AP79+AP80,AP74) -> 48307.399 | AQ82: =IF(AQ81="NO",AQ79+AQ80,AQ74) -> 53056.072 | AR82: =IF(AR81="NO",AR79+AR80,AR74) -> 45573.116 | AS82: =IF(AS81="NO",AS79+AS80,AS74) -> 5904.6356 | ... AW82: =IF(AW81="NO",AW79+AW80,AW74) -> 912.63026
F83: FFL to Equity | J83: =(J79+J80)-J82 -> 0 | K83: =(K79+K80)-K82 -> 0 | L83: =(L79+L80)-L82 -> 0 | M83: =M79-M82 -> 0 | N83: =N79-N82 -> 0 | O83: =O79-O82 -> 0 | P83: =IF(P81="Si",P79-P82,0) -> 0 | Q83: =Q79-Q82 -> 0 | R83: =R79-R82 -> 0 | S83: =S79-S82 -> 0 | T83: =T79-T82 -> 0 | U83: =U79-U82 -> 106633.8 | X83: =(X79+X80)-X82 -> 0 | Y83: =(Y79+Y80)-Y82 -> 0 | Z83: =(Z79+Z80)-Z82 -> 0 | AA83: =AA79-AA82 -> 0 | AB83: =AB79-AB82 -> 0 | AC83: =AC79-AC82 -> 0 | AD83: =IF(AD81="Si",AD79-AD82,0) -> 0 | AE83: =AE79-AE82 -> 0 | AF83: =AF79-AF82 -> 0 | AG83: =AG79-AG82 -> 0 | AH83: =AH79-AH82 -> 0 | AI83: =AI79-AI82 -> 188855.54 | AL83: =(AL79+AL80)-AL82 -> 0 | AM83: =(AM79+AM80)-AM82 -> 0 | AN83: =(AN79+AN80)-AN82 -> 0 | AO83: =AO79-AO82 -> 43494.674 | AP83: =AP79-AP82 -> 0 | AQ83: =AQ79-AQ82 -> 0 | AR83: =IF(AR81="Si",AR79-AR82,0) -> 0 | AS83: =AS79-AS82 -> 45573.116 | AT83: =AT79-AT82 -> 0 | AU83: =AU79-AU82 -> 0 | AV83: =AV79-AV82 -> 0 | AW83: =AW79-AW82 -> 45502.498
J84: =IF(J83>0,"REPARTIJA","") | K84: =IF(K83>0,"REPARTIJA","") | L84: =IF(L83>0,"REPARTIJA","") | M84: =IF(M83>0,"REPARTIJA","") | N84: =IF(N83>0,"REPARTIJA","") | O84: =IF(O83>0,"REPARTIJA","") | P84: =IF(P83>0,"REPARTIJA","") | Q84: =IF(Q83>0,"REPARTIJA","") | ... U84: =IF(U83>0,"REPARTIJA","") -> REPARTIJA | X84: =IF(X83>0,"REPARTIJA","") | Y84: =IF(Y83>0,"REPARTIJA","") | Z84: =IF(Z83>0,"REPARTIJA","") | AA84: =IF(AA83>0,"REPARTIJA","") | AB84: =IF(AB83>0,"REPARTIJA","") | AC84: =IF(AC83>0,"REPARTIJA","") | AD84: =IF(AD83>0,"REPARTIJA","") | AE84: =IF(AE83>0,"REPARTIJA","") | ... AI84: =IF(AI83>0,"REPARTIJA","") -> REPARTIJA | AL84: =IF(AL83>0,"REPARTIJA","") | AM84: =IF(AM83>0,"REPARTIJA","") | AN84: =IF(AN83>0,"REPARTIJA","") | AO84: =IF(AO83>0,"REPARTIJA","") -> REPARTIJA | AP84: =IF(AP83>0,"REPARTIJA","") | AQ84: =IF(AQ83>0,"REPARTIJA","") | AR84: =IF(AR83>0,"REPARTIJA","") | AS84: =IF(AS83>0,"REPARTIJA","") -> REPARTIJA | ... AW84: =IF(AW83>0,"REPARTIJA","") -> REPARTIJA
F87: Acumulado Aguinaldo | J87: =-J71 -> 2359.1549 | K87: =-K71+J87 -> 4718.3099 | L87: =-L71+K87 -> 7077.4648 | M87: =-M71+L87 -> 9718.3099 | N87: 0 | O87: =-O71 -> 2359.1549 | P87: =-P71+O87 -> 4718.3099 | Q87: =-Q71+P87 -> 7359.1549 | R87: =-R71+Q87 -> 10000 | S87: =-S71+R87 -> 12640.845 | T87: =-T71+S87 -> 15281.69 | U87: 0 | X87: =-X71 -> 3521.1268 | Y87: =-Y71+X87 -> 7042.2535 | Z87: =-Z71+Y87 -> 10563.38 | AA87: =-AA71+Z87 -> 14084.507 | AB87: 0 | AC87: =-AC71 -> 3521.1268 | AD87: =-AD71+AC87 -> 7042.2535 | AE87: =-AE71+AD87 -> 10563.38 | AF87: =-AF71+AE87 -> 14084.507 | AG87: =-AG71+AF87 -> 17605.634 | AH87: =-AH71+AG87 -> 21126.761 | AI87: 0 | AL87: =-AL71 -> 3521.1268 | AM87: =-AM71+AL87 -> 7042.2535 | AN87: =-AN71+AM87 -> 10563.38 | AO87: =-AO71+AN87 -> 14084.507 | AP87: 0 | AQ87: =-AQ71 -> 3521.1268 | AR87: =-AR71+AQ87 -> 7042.2535 | AS87: =-AS71+AR87 -> 10563.38 | AT87: =-AT71+AS87 -> 14084.507 | AU87: =-AU71+AT87 -> 17605.634 | AV87: =-AV71+AU87 -> 21126.761 | AW87: 0
F88: Prevision Impuestos | J88: =-J72 -> 0 | K88: =-K72+J88 -> -161.58705 | L88: =-L72+K88 -> -218.63847 | M88: =-M72+L88 -> 1018.7888 | N88: =-N72+M88 -> 1410.5041 | O88: =-O72+N88 -> 1410.5041 | P88: =-P72+O88 -> 1429.9725 | Q88: =-Q72+P88 -> 2428.3367 | R88: =-R72+Q88 -> 3696.4714 | ... U88: =-U72+T88 -> 7027.2069 | X88: =-X72 -> 0 | Y88: =-Y72+X88 -> -1369.3352 | Z88: =-Z72+Y88 -> -2564.4444 | AA88: =-AA72+Z88 -> 364.21403 | AB88: =-AB72+AA88 -> 1991.7772 | AC88: =-AC72+AB88 -> 2097.9735 | AD88: =-AD72+AC88 -> 2563.1999 | AE88: =-AE72+AD88 -> 4310.8546 | AF88: =-AF72+AE88 -> 6065.3539 | ... AI88: =-AI72+AH88 -> 9174.0487 | AL88: =-AL72 -> -648.84261 | AM88: =-AM72+AL88 -> -1572.0347 | AN88: =-AN72+AM88 -> -2336.8394 | AO88: =-AO72+AN88 -> 3.9191901 | AP88: =-AP72+AO88 -> 1161.8639 | AQ88: =-AQ72+AP88 -> 1161.8639 | AR88: =-AR72+AQ88 -> 1263.1389 | AS88: =-AS72+AR88 -> 2530.2577 | AT88: =-AT72+AS88 -> 3803.5989 | ... AW88: =-AW72+AV88 -> 5664.7107
F89: Reserva para despidos | J89: =-J73 -> 993.40574 | K89: =-K73+J89 -> 2148.1292 | L89: =-L73+K89 -> 3302.8526 | M89: =-M73+L89 -> 4457.5761 | N89: =-N73+M89 -> 5612.2995 | O89: =-O73+N89 -> 6767.023 | P89: =-P73+O89 -> 7921.7464 | Q89: =-Q73+P89 -> 9076.4699 | R89: =-R73+Q89 -> 10231.193 | ... U89: =-U73+T89 -> 13695.364 | X89: =-X73 -> 1083.7154 | Y89: =-Y73+X89 -> 3008.2544 | Z89: =-Z73+Y89 -> 4932.7935 | AA89: =-AA73+Z89 -> 6857.3326 | AB89: =-AB73+AA89 -> 8781.8717 | AC89: =-AC73+AB89 -> 10706.411 | AD89: =-AD73+AC89 -> 12630.95 | AE89: =-AE73+AD89 -> 14555.489 | AF89: =-AF73+AE89 -> 16480.028 | ... AI89: =-AI73+AH89 -> 22253.645 | AL89: =-AL73 -> 1641.993 | AM89: =-AM73+AL89 -> 3391.5739 | AN89: =-AN73+AM89 -> 5141.1549 | AO89: =-AO73+AN89 -> 6890.7359 | AP89: =-AP73+AO89 -> 8640.3169 | AQ89: =-AQ73+AP89 -> 10389.898 | AR89: =-AR73+AQ89 -> 12139.479 | AS89: =-AS73+AR89 -> 13889.06 | AT89: =-AT73+AS89 -> 15638.641 | ... AW89: =-AW73+AV89 -> 20887.384
W90: Hasta que monto previsionamos? | AK90: Hasta que monto previsionamos?
F91: Meses | I91: 0 | J91: 1 | K91: 2 | L91: 3 | M91: 4 | N91: 5 | O91: 6 | P91: 7 | Q91: 8 | R91: 9 | S91: 10 | T91: 11 | U91: 12 | X91: 13 | Y91: 14 | Z91: 15 | AA91: 16 | AB91: 17 | AC91: 18 | AD91: 19 | AE91: 20 | AF91: 21 | AG91: 22 | AH91: 23 | AI91: 24 | AL91: 25 | AM91: 26 | AN91: 27 | AO91: 28 | AP91: 29 | AQ91: 30 | AR91: 31 | AS91: 32 | AT91: 33 | AU91: 34 | AV91: 35 | AW91: 36
F92: Payback | I92: =I74 -> -431000 | J92: =I92+J83 -> -431000 | K92: =J92+K83 -> -431000 | L92: =K92+L83 -> -431000 | M92: =L92+M83 -> -431000 | N92: =M92+N83 -> -431000 | O92: =N92+O83 -> -431000 | P92: =O92+P83 -> -431000 | Q92: =P92+Q83 -> -431000 | ... U92: =T92+U83 -> -324366.2 | X92: =U92+X83 -> -324366.2 | Y92: =X92+Y83 -> -324366.2 | Z92: =Y92+Z83 -> -324366.2 | AA92: =Z92+AA83 -> -324366.2 | AB92: =AA92+AB83 -> -324366.2 | AC92: =AB92+AC83 -> -324366.2 | AD92: =AC92+AD83 -> -324366.2 | AE92: =AD92+AE83 -> -324366.2 | AF92: =AE92+AF83 -> -324366.2 | ... AI92: =AH92+AI83 -> -135510.67 | AL92: =AI92+AL83 -> -135510.67 | AM92: =AL92+AM83 -> -135510.67 | AN92: =AM92+AN83 -> -135510.67 | AO92: =AN92+AO83 -> -92015.991 | AP92: =AO92+AP83 -> -92015.991 | AQ92: =AP92+AQ83 -> -92015.991 | AR92: =AQ92+AR83 -> -92015.991 | AS92: =AR92+AS83 -> -46442.876 | AT92: =AS92+AT83 -> -46442.876 | ... AW92: =AV92+AW83 -> -940.37722
F93: Payback Logrado? | I93: =IF(I92<0,"No","Si") -> No | J93: =IF(J92<0,"No","Si") -> No | K93: =IF(K92<0,"No","Si") -> No | L93: =IF(L92<0,"No","Si") -> No | M93: =IF(M92<0,"No","Si") -> No | N93: =IF(N92<0,"No","Si") -> No | O93: =IF(O92<0,"No","Si") -> No | P93: =IF(P92<0,"No","Si") -> No | ... U93: =IF(U92<0,"No","Si") -> No | X93: =IF(X92<0,"No","Si") -> No | Y93: =IF(Y92<0,"No","Si") -> No | Z93: =IF(Z92<0,"No","Si") -> No | AA93: =IF(AA92<0,"No","Si") -> No | AB93: =IF(AB92<0,"No","Si") -> No | AC93: =IF(AC92<0,"No","Si") -> No | AD93: =IF(AD92<0,"No","Si") -> No | AE93: =IF(AE92<0,"No","Si") -> No | ... AI93: =IF(AI92<0,"No","Si") -> No | AL93: =IF(AL92<0,"No","Si") -> No | AM93: =IF(AM92<0,"No","Si") -> No | AN93: =IF(AN92<0,"No","Si") -> No | AO93: =IF(AO92<0,"No","Si") -> No | AP93: =IF(AP92<0,"No","Si") -> No | AQ93: =IF(AQ92<0,"No","Si") -> No | AR93: =IF(AR92<0,"No","Si") -> No | AS93: =IF(AS92<0,"No","Si") -> No | ... AW93: =IF(AW92<0,"No","Si") -> No
F94: Mes de Payback | I94: =IF(AND(H93="No",I93="Si"),"PAYBACK","") | J94: =IF(AND(I93="No",J93="Si"),"PAYBACK","") | K94: =IF(AND(J93="No",K93="Si"),"PAYBACK","") | L94: =IF(AND(K93="No",L93="Si"),"PAYBACK","") | M94: =IF(AND(L93="No",M93="Si"),"PAYBACK","") | N94: =IF(AND(M93="No",N93="Si"),"PAYBACK","") | O94: =IF(AND(N93="No",O93="Si"),"PAYBACK","") | P94: =IF(AND(O93="No",P93="Si"),"PAYBACK","") | ... U94: =IF(AND(T93="No",U93="Si"),"PAYBACK","") | X94: =IF(AND(U93="No",X93="Si"),"PAYBACK","") | Y94: =IF(AND(X93="No",Y93="Si"),"PAYBACK","") | Z94: =IF(AND(Y93="No",Z93="Si"),"PAYBACK","") | AA94: =IF(AND(Z93="No",AA93="Si"),"PAYBACK","") | AB94: =IF(AND(AA93="No",AB93="Si"),"PAYBACK","") | AC94: =IF(AND(AB93="No",AC93="Si"),"PAYBACK","") | AD94: =IF(AND(AC93="No",AD93="Si"),"PAYBACK","") | AE94: =IF(AND(AD93="No",AE93="Si"),"PAYBACK","") | AF94: =IF(AND(AE93="No",AF93="Si"),"PAYBACK","") | ... AI94: =IF(AND(AH93="No",AI93="Si"),"PAYBACK","") | AL94: =IF(AND(AI93="No",AL93="Si"),"PAYBACK","") | AM94: =IF(AND(AL93="No",AM93="Si"),"PAYBACK","") | AN94: =IF(AND(AM93="No",AN93="Si"),"PAYBACK","") | AO94: =IF(AND(AN93="No",AO93="Si"),"PAYBACK","") | AP94: =IF(AND(AO93="No",AP93="Si"),"PAYBACK","") | AQ94: =IF(AND(AP93="No",AQ93="Si"),"PAYBACK","") | AR94: =IF(AND(AQ93="No",AR93="Si"),"PAYBACK","") | AS94: =IF(AND(AR93="No",AS93="Si"),"PAYBACK","") | AT94: =IF(AND(AS93="No",AT93="Si"),"PAYBACK","") | ... AW94: =IF(AND(AV93="No",AW93="Si"),"PAYBACK","")
F97: ANALISIS DE SENSIBILIDAD
G100: Sensibilidad del VAN contra Ventas y Ticket Promedio | P100: Sensibilidad del VAN contra Nomina y CMV
H102: Ticket Promedio | Q102: Gasto de Nómina
G103: =C35 -> 399459.45 | H103: 20000 | I103: 25000 | J103: 30000 | K103: 35000 | L103: 40000 | P103: =C35 -> 399459.45 | Q103: 45000000 | R103: 50000000 | S103: 55000000 | T103: 60000000 | U103: 65000000
F104: Precision Ventas Proyectadas | G104: 0.8 | H104: -431000 | I104: -431000 | J104: -431000 | K104: -59993.56 | L104: 470672.11 | O104: CMV | P104: 0.27 | Q104: 1631535.2 | R104: 1430667.6 | S104: 1229800 | T104: 1028781.4 | U104: 827696.89
G105: 0.85 | H105: -431000 | I105: -431000 | J105: -334607.51 | K105: 149229.56 | L105: 755522.73 | P105: 0.28 | Q105: 1541710.9 | R105: 1340843.3 | S105: 1139962.8 | T105: 938878.26 | U105: 737793.76
G106: 0.9 | H106: -431000 | I106: -431000 | J106: -174447.67 | K106: 399459.45 | L106: 1040373.3 | P106: 0.29 | Q106: 1451886.6 | R106: 1251019 | S106: 1050059.6 | T106: 848975.12 | U106: 647890.63
G107: 0.95 | H107: -431000 | I107: -431000 | J107: -1451.6511 | K107: 648703.75 | L107: 1325097.1 | P107: 0.3 | Q107: 1362062.3 | R107: 1161194.7 | S107: 960156.49 | T107: 759071.99 | U107: 557987.49
G108: 1 | H108: -431000 | I108: -388024.49 | J108: 185100.29 | K108: 897948.04 | L108: 1609692.5 | P108: 0.31 | Q108: 1272238 | R108: 1071337.9 | S108: 870253.35 | T108: 669168.86 | U108: 468084.36
G109: 1.05 | H109: -431000 | I109: -254482.03 | J109: 399459.45 | K109: 1147192.3 | L109: 1894287.9 | P109: 0.32 | Q109: 1182413.7 | R109: 981434.72 | S109: 780350.22 | T109: 579265.72 | U109: 378181.23
G110: 1.1 | H110: -431000 | I110: -118959.39 | J110: 613097.42 | K110: 1396246 | L110: 2178883.3 | P110: 0.33 | Q110: 1092589.4 | R110: 891531.58 | S110: 690447.09 | T110: 489362.59 | U110: 288085.09
P111: 0.34 | Q111: 1002712.9 | R111: 801628.45 | S111: 600543.95 | T111: 399459.45 | U111: 197528.71
P112: 0.35 | Q112: 912809.81 | R112: 711725.32 | S112: 510640.82 | T112: 309496.11 | U112: 114580.16
P113: 0.36 | Q113: 822906.68 | R113: 621822.18 | S113: 420737.68 | T113: 219211.95 | U113: 41307.536
P114: 0.37 | Q114: 733003.54 | R114: 531919.05 | S114: 330804.7 | T114: 128655.58 | U114: -32315.728
P115: 0.38 | Q115: 643100.41 | R115: 442015.91 | S115: 240808.31 | T115: 53949.488 | U115: -106524.28

Sheet Cash Flow
E1: 0 | F1: 1 | G1: 2 | H1: 3 | I1: 4 | J1: 5 | K1: 6 | L1: 7 | M1: 8 | N1: 9 | O1: 10
B3: TC | E3: 1420 | F3: 1420 | G3: 1420 | H3: 1420 | I3: 1420 | J3: 1420 | K3: 1420 | L3: 1420 | M3: 1420 | N3: 1420 | O3: 1420
B4: Evolución esperada del riesgo país | E4: 0.05 | F4: 0.03 | G4: 0.01 | H4: 0.01 | I4: 0.01 | J4: 0.01 | K4: 0.01 | L4: 0.01 | M4: 0.01 | N4: 0.01 | O4: 0.01 | P4: 0.01
B5: Kwacc | E5: =+(1-H26)*D26+H26*D24*(1-H27) -> 0.22808944 | F5: =$D$30+($H$25*($D$33+F4+$D$36+$D$37)) -> 0.17855344 | G5: =$D$30+($H$25*($D$33+G4+$D$36+$D$37)) -> 0.16309744 | H5: =$D$30+($H$25*($D$33+H4+$D$36+$D$37)) -> 0.16309744 | I5: =$D$30+($H$25*($D$33+I4+$D$36+$D$37)) -> 0.16309744 | J5: =$D$30+($H$25*($D$33+J4+$D$36+$D$37)) -> 0.16309744 | K5: =$D$30+($H$25*($D$33+K4+$D$36+$D$37)) -> 0.16309744 | L5: =$D$30+($H$25*($D$33+L4+$D$36+$D$37)) -> 0.16309744 | M5: =$D$30+($H$25*($D$33+M4+$D$36+$D$37)) -> 0.16309744 | ... P5: =$D$30+($H$25*($D$33+P4+$D$36+$D$37)) -> 0.16309744
B6: Cash Flow | D6: Unidad | E6: Año 0 | F6: Año 1 | G6: Año 2 | H6: Año 3 | I6: Año 4 | J6: Año 5 | K6: Año 6 | L6: Año 7 | M6: Año 8 | N6: Año 9 | O6: Año 10 | P6: Año 11
B7: NOPAT | D7: USD | F7: =SUM('EERR Mensual'!J62:U62) -> 128548.24 | G7: =SUM('EERR Mensual'!X62:AI62) -> 256260.51 | H7: =G7 -> 256260.51 | I7: =H7 -> 256260.51 | J7: =I7 -> 256260.51 | K7: =J7 -> 256260.51 | L7: =K7 -> 256260.51 | M7: =L7 -> 256260.51 | N7: =M7 -> 256260.51 | O7: =N7 -> 256260.51 | P7: =O7*(1+S10) -> 263948.32 | R7: Ronic | S7: 0.1
B8: FFL | D8: USD | E8: ='EERR Mensual'!I74 -> -431000 | F8: ='EERR Mensual'!U83 -> 106633.8 | G8: ='EERR Mensual'!AI83 -> 188855.54 | H8: =G8 -> 188855.54 | I8: =H8 -> 188855.54 | J8: =I8 -> 188855.54 | K8: =J8 -> 188855.54 | L8: =K8 -> 188855.54 | M8: =L8 -> 188855.54 | N8: =M8 -> 188855.54 | O8: =N8 -> 188855.54 | P8: =P7*(1-S8) -> 184763.82 | R8: TRI | S8: =S10/S7 -> 0.3
B9: Valor Residual FFL | D9: USD | O9: =IF(F14="Si",P8/(P5-S10),0) -> 0
B10: FFL + Valor Residual | D10: USD | E10: =E8+E9 -> -431000 | F10: =F8+F9 -> 106633.8 | G10: =G8+G9 -> 188855.54 | H10: =H8+H9 -> 188855.54 | I10: =I8+I9 -> 188855.54 | J10: =J8+J9 -> 188855.54 | K10: =K8+K9 -> 188855.54 | L10: =L8+L9 -> 188855.54 | ... O10: =O8+O9 -> 188855.54 | R10: g | S10: =[1]DASHBOARD!C8 -> 0.03
B11: Factor de descuento | D11: USD | E11: =1/(1+$E$5)^0 -> 1 | F11: =1/(1+F5)^F1 -> 0.8484978 | G11: =1/(1+G5)^G1 -> 0.73920994 | H11: =1/(1+H5)^H1 -> 0.63555289 | I11: =1/(1+I5)^I1 -> 0.54643134 | J11: =1/(1+J5)^J1 -> 0.46980702 | K11: =1/(1+K5)^K1 -> 0.40392748 | L11: =1/(1+L5)^L1 -> 0.34728602 | M11: =1/(1+M5)^M1 -> 0.29858721 | ... O11: =1/(1+O5)^O1 -> 0.22071863
B12: Valor presente de FFL + VR FFL | D12: USD | E12: =E10*E11 -> -431000 | F12: =F10*F11 -> 90478.542 | G12: =G10*G11 -> 139603.89 | H12: =H10*H11 -> 120027.68 | I12: =I10*I11 -> 103196.58 | J12: =J10*J11 -> 88725.657 | K12: =K10*K11 -> 76283.942 | L12: =L10*L11 -> 65586.888 | ... O12: =O10*O11 -> 41683.937
B14: VAN | C14: =SUM(E12:O12) -> 399459.45 | E14: VALOR RESIDUAL | F14: No
B16: TIR | C16: =IRR(E10:O10,0.1) -> 0.36776345
B20: VALUACIÓN POR WACC
B22: TASAS DE DESCUENTO
B24: Kd | D24: =+D30+D34 -> 0.0479 | G24: Beta desapalancada | H24: =D31*(1-D32) -> 0.7728
B25: Ku | D25: =+D30+D33*H24+D35 -> 0.12808944 | G25: Beta re-apalancada | H25: =+H24*(1+H26/(1-H26)) -> 0.7728
B26: Ke | D26: =+D30+(D33*H25)+D35+D36+D37 -> 0.22808944 | G26: D/V | H26: 0
B27: Kwacc | D27: =+(1-H26)*D26+H26*D24*(1-H27) -> 0.22808944 | G27: t | H27: 0.35
B29: INPUTS PARA TASA DESCUENTO
B30: Bonos de tesoro USA - 10Y | D30: 0.0454 | G30: Risk Free Rate | H30: =D30 -> 0.0454
B31: Beta aplancada de la industria | D31: 0.92 | E31: Damodaran - Restaurant Dining | G31: Bu | H31: =H24 -> 0.7728
B32: D/V de la industria | D32: 0.16 | G32: ERP | H32: =D33 -> 0.0423
B33: Prima de riesgo mercado | D33: 0.0423 | E33: Damodaran | G33: Riesgo País | H33: =D35 -> 0.05
B34: Prima de riesgo no pago de la deuda | D34: 0.0025 | G34: Ke | H34: =D26 -> 0.22808944
B35: Prima de riesgo país | D35: 0.05 | E35: JPMORGAN EMBI+ | G35: Wacc | H35: =H34 -> 0.22808944
B36: Prima por Iliquidez | D36: 0.05
B37: Prima por empresa chica | D37: 0.05

Sheet ITEMS
B2: ITEM | C2: Nota Diego | D2: Inputs Gastón
B3: Ver el Ramp Up de ventas | C3: Puse un modificador para llegar a los clientes esperados. Estaba puesto como que arranca el primer mes al palo. Lo más probable es que no arranquemos el 1 del mes, o que tarde unos meses en venir la clientela que queremos.
B4: Ver si las ventas crecen en año 2 y subsiguientes | C4: Puse ventas constantes, pero asumo que el segundo año si todo va bien hay lugar para crecer en ventas.
B5: Ver días de caja necesaria
B6: Ver días de clientes | C6: Hay que ver bien cuándo entra la guita. Si hay un porcentaje de comisión de 11% en el EERR, eso es porque reciben la guita en el momento y ahí están las comisiones por ello?
B7: Ver días de proveedores | C7: Hay que ver a cuántos días se les puede pagar a los proveedores, particularmente a los de materia prima. Los empleados y costos fijos como alquiiler asumimos son a mes vencido.
B8: Ver comisiones / Impuestos | C8: En qué momento se pagan?
B9: Ver impueso a las ganancias | C9: Puse 10%, cuánto puede ser? | D9: Es 5
B10: Ver Ticket Promedio | C10: Este item es bastante crítico. Ver análisis de sensibilidad.
B11: Ver Prevision para despidos | C11: Hasta qué monto guardamos? Esto debiera ir a una cuenta remunerada en dólares. | D11: Topear en 10.000 usd
B12: Ver monto servicios públicos | C12: Está fijo en 6.800.000, debiera ser variable con actividad. Ver cómo calzan los pagos porque impacta en los primeros meses en la caja necesaria para arrancar.
B13: Ver estructura de bonos | C13: No hay nada puesto, cómo lo pensaron esto?
B14: Ver items como inversión, bazar, etc | C14: Cuánto hay que guardar de esto?
B15: Ver RRHH | C15: Entender cómo funciona la cantidad de gente y si hay aumento temporal durante temporada alta. Puse 60 millones para redondear. REVISAR! | D15: Ya lo vimos
B16: El marketing debiera ir como costo fijo. Si vendés CERO, entonces invertís cero en MKT? | C16: Quién maneja esto? Habría que invertir más al inicio para darse a conocer.
B17: VER CUSTOMER JOURNEY + FUNNEL | C17: Tienen hecho esto para el CDB?
B18: Chequear CAPEX final
B19: Revisar cada item y linea del EERR y el Cashflow
B20: Prevision de aguinaldos | C20: Debiera ir a una cuenta money market o similar.
B21: Prevision de impuestos | C21: Debiera ir a una cuenta money market o similar. En pesos o en usd? Si el dólar baja y está en usd cagamos, viceversa ganamos.
B22: Anticipos de ganancias | C22: Esto no está contemplado
B23: IVA | C23: Esto tampoco está contemplado. Entender bien el manejo de esto y como impacta.
B24: TIPO de cambio | C24: Lo dejé constante. Lo más probable es que baje, mejorando los ingresos en dólares. Por simplicidad lo dejaría fijo.
